[{"MeasureID":18,"GeoType":"Borough","GeoID":1,"Time":"2013","ban_summary_flag":0,"Value":1.01,"CI":"","Note":"","DisplayValue":"1.0"},{"MeasureID":18,"GeoType":"Borough","GeoID":1,"Time":"2012","ban_summary_flag":0,"Value":1.07,"CI":"","Note":"","DisplayValue":"1.1"},{"MeasureID":18,"GeoType":"Borough","GeoID":1,"Time":"2011","ban_summary_flag":0,"Value":1.02,"CI":"","Note":"","DisplayValue":"1.0"},{"MeasureID":18,"GeoType":"Borough","GeoID":1,"Time":"2010","ban_summary_flag":0,"Value":1.03,"CI":"","Note":"","DisplayValue":"1.0"},{"MeasureID":18,"GeoType":"Borough","GeoID":1,"Time":"2009","ban_summary_flag":0,"Value":1.04,"CI":"","Note":"","DisplayValue":"1.0"},{"MeasureID":18,"GeoType":"Borough","GeoID":1,"Time":"2008","ban_summary_flag":0,"Value":1.07,"CI":"","Note":"","DisplayValue":"1.1"},{"MeasureID":18,"GeoType":"Borough","GeoID":1,"Time":"2007","ban_summary_flag":0,"Value":1.03,"CI":"","Note":"","DisplayValue":"1.0"},{"MeasureID":18,"GeoType":"Borough","GeoID":1,"Time":"2006","ban_summary_flag":0,"Value":1.01,"CI":"","Note":"","DisplayValue":"1.0"},{"MeasureID":18,"GeoType":"Borough","GeoID":1,"Time":"2005","ban_summary_flag":0,"Value":1.06,"CI":"","Note":"","DisplayValue":"1.1"},{"MeasureID":18,"GeoType":"Borough","GeoID":1,"Time":"2004","ban_summary_flag":0,"Value":1.02,"CI":"","Note":"","DisplayValue":"1.0"},{"MeasureID":18,"GeoType":"Borough","GeoID":1,"Time":"2003","ban_summary_flag":0,"Value":1.05,"CI":"","Note":"","DisplayValue":"1.0"},{"MeasureID":18,"GeoType":"Borough","GeoID":1,"Time":"2002","ban_summary_flag":0,"Value":1.04,"CI":"","Note":"","DisplayValue":"1.0"},{"MeasureID":18,"GeoType":"Borough","GeoID":1,"Time":"2001","ban_summary_flag":0,"Value":1.02,"CI":"","Note":"","DisplayValue":"1.0"},{"MeasureID":18,"GeoType":"Borough","GeoID":1,"Time":"2000","ban_summary_flag":0,"Value":1.05,"CI":"","Note":"","DisplayValue":"1.0"},{"MeasureID":18,"GeoType":"Borough","GeoID":1,"Time":"1999","ban_summary_flag":0,"Value":1.02,"CI":"","Note":"","DisplayValue":"1.0"},{"MeasureID":18,"GeoType":"Borough","GeoID":1,"Time":"1998","ban_summary_flag":0,"Value":1.05,"CI":"","Note":"","DisplayValue":"1.0"},{"MeasureID":18,"GeoType":"Borough","GeoID":2,"Time":"2013","ban_summary_flag":0,"Value":1.05,"CI":"","Note":"","DisplayValue":"1.0"},{"MeasureID":18,"GeoType":"Borough","GeoID":2,"Time":"2012","ban_summary_flag":0,"Value":1.03,"CI":"","Note":"","DisplayValue":"1.0"},{"MeasureID":18,"GeoType":"Borough","GeoID":2,"Time":"2011","ban_summary_flag":0,"Value":1.05,"CI":"","Note":"","DisplayValue":"1.0"},{"MeasureID":18,"GeoType":"Borough","GeoID":2,"Time":"2010","ban_summary_flag":0,"Value":1.06,"CI":"","Note":"","DisplayValue":"1.1"},{"MeasureID":18,"GeoType":"Borough","GeoID":2,"Time":"2009","ban_summary_flag":0,"Value":1.05,"CI":"","Note":"","DisplayValue":"1.0"},{"MeasureID":18,"GeoType":"Borough","GeoID":2,"Time":"2008","ban_summary_flag":0,"Value":1.04,"CI":"","Note":"","DisplayValue":"1.0"},{"MeasureID":18,"GeoType":"Borough","GeoID":2,"Time":"2007","ban_summary_flag":0,"Value":1.04,"CI":"","Note":"","DisplayValue":"1.0"},{"MeasureID":18,"GeoType":"Borough","GeoID":2,"Time":"2006","ban_summary_flag":0,"Value":1.06,"CI":"","Note":"","DisplayValue":"1.1"},{"MeasureID":18,"GeoType":"Borough","GeoID":2,"Time":"2005","ban_summary_flag":0,"Value":1.04,"CI":"","Note":"","DisplayValue":"1.0"},{"MeasureID":18,"GeoType":"Borough","GeoID":2,"Time":"2004","ban_summary_flag":0,"Value":1.04,"CI":"","Note":"","DisplayValue":"1.0"},{"MeasureID":18,"GeoType":"Borough","GeoID":2,"Time":"2003","ban_summary_flag":0,"Value":1.05,"CI":"","Note":"","DisplayValue":"1.0"},{"MeasureID":18,"GeoType":"Borough","GeoID":2,"Time":"2002","ban_summary_flag":0,"Value":1.04,"CI":"","Note":"","DisplayValue":"1.0"},{"MeasureID":18,"GeoType":"Borough","GeoID":2,"Time":"2001","ban_summary_flag":0,"Value":1.06,"CI":"","Note":"","DisplayValue":"1.1"},{"MeasureID":18,"GeoType":"Borough","GeoID":2,"Time":"2000","ban_summary_flag":0,"Value":1.04,"CI":"","Note":"","DisplayValue":"1.0"},{"MeasureID":18,"GeoType":"Borough","GeoID":2,"Time":"1999","ban_summary_flag":0,"Value":1.03,"CI":"","Note":"","DisplayValue":"1.0"},{"MeasureID":18,"GeoType":"Borough","GeoID":2,"Time":"1998","ban_summary_flag":0,"Value":1.06,"CI":"","Note":"","DisplayValue":"1.1"},{"MeasureID":18,"GeoType":"Borough","GeoID":3,"Time":"2013","ban_summary_flag":0,"Value":1.05,"CI":"","Note":"","DisplayValue":"1.0"},{"MeasureID":18,"GeoType":"Borough","GeoID":3,"Time":"2012","ban_summary_flag":0,"Value":1.05,"CI":"","Note":"","DisplayValue":"1.0"},{"MeasureID":18,"GeoType":"Borough","GeoID":3,"Time":"2011","ban_summary_flag":0,"Value":1.03,"CI":"","Note":"","DisplayValue":"1.0"},{"MeasureID":18,"GeoType":"Borough","GeoID":3,"Time":"2010","ban_summary_flag":0,"Value":1.04,"CI":"","Note":"","DisplayValue":"1.0"},{"MeasureID":18,"GeoType":"Borough","GeoID":3,"Time":"2009","ban_summary_flag":0,"Value":1.04,"CI":"","Note":"","DisplayValue":"1.0"},{"MeasureID":18,"GeoType":"Borough","GeoID":3,"Time":"2008","ban_summary_flag":0,"Value":1.06,"CI":"","Note":"","DisplayValue":"1.1"},{"MeasureID":18,"GeoType":"Borough","GeoID":3,"Time":"2007","ban_summary_flag":0,"Value":1.02,"CI":"","Note":"","DisplayValue":"1.0"},{"MeasureID":18,"GeoType":"Borough","GeoID":3,"Time":"2006","ban_summary_flag":0,"Value":1.05,"CI":"","Note":"","DisplayValue":"1.0"},{"MeasureID":18,"GeoType":"Borough","GeoID":3,"Time":"2005","ban_summary_flag":0,"Value":1.05,"CI":"","Note":"","DisplayValue":"1.0"},{"MeasureID":18,"GeoType":"Borough","GeoID":3,"Time":"2004","ban_summary_flag":0,"Value":1.03,"CI":"","Note":"","DisplayValue":"1.0"},{"MeasureID":18,"GeoType":"Borough","GeoID":3,"Time":"2003","ban_summary_flag":0,"Value":1.06,"CI":"","Note":"","DisplayValue":"1.1"},{"MeasureID":18,"GeoType":"Borough","GeoID":3,"Time":"2002","ban_summary_flag":0,"Value":1.04,"CI":"","Note":"","DisplayValue":"1.0"},{"MeasureID":18,"GeoType":"Borough","GeoID":3,"Time":"2001","ban_summary_flag":0,"Value":1.06,"CI":"","Note":"","DisplayValue":"1.1"},{"MeasureID":18,"GeoType":"Borough","GeoID":3,"Time":"2000","ban_summary_flag":0,"Value":1.04,"CI":"","Note":"","DisplayValue":"1.0"},{"MeasureID":18,"GeoType":"Borough","GeoID":3,"Time":"1999","ban_summary_flag":0,"Value":1.07,"CI":"","Note":"","DisplayValue":"1.1"},{"MeasureID":18,"GeoType":"Borough","GeoID":3,"Time":"1998","ban_summary_flag":0,"Value":1.04,"CI":"","Note":"","DisplayValue":"1.0"},{"MeasureID":18,"GeoType":"Borough","GeoID":4,"Time":"2013","ban_summary_flag":0,"Value":1.04,"CI":"","Note":"","DisplayValue":"1.0"},{"MeasureID":18,"GeoType":"Borough","GeoID":4,"Time":"2012","ban_summary_flag":0,"Value":1.06,"CI":"","Note":"","DisplayValue":"1.1"},{"MeasureID":18,"GeoType":"Borough","GeoID":4,"Time":"2011","ban_summary_flag":0,"Value":1.05,"CI":"","Note":"","DisplayValue":"1.0"},{"MeasureID":18,"GeoType":"Borough","GeoID":4,"Time":"2010","ban_summary_flag":0,"Value":1.05,"CI":"","Note":"","DisplayValue":"1.0"},{"MeasureID":18,"GeoType":"Borough","GeoID":4,"Time":"2009","ban_summary_flag":0,"Value":1.05,"CI":"","Note":"","DisplayValue":"1.0"},{"MeasureID":18,"GeoType":"Borough","GeoID":4,"Time":"2008","ban_summary_flag":0,"Value":1.05,"CI":"","Note":"","DisplayValue":"1.0"},{"MeasureID":18,"GeoType":"Borough","GeoID":4,"Time":"2007","ban_summary_flag":0,"Value":1.04,"CI":"","Note":"","DisplayValue":"1.0"},{"MeasureID":18,"GeoType":"Borough","GeoID":4,"Time":"2006","ban_summary_flag":0,"Value":1.04,"CI":"","Note":"","DisplayValue":"1.0"},{"MeasureID":18,"GeoType":"Borough","GeoID":4,"Time":"2005","ban_summary_flag":0,"Value":1.04,"CI":"","Note":"","DisplayValue":"1.0"},{"MeasureID":18,"GeoType":"Borough","GeoID":4,"Time":"2004","ban_summary_flag":0,"Value":1.05,"CI":"","Note":"","DisplayValue":"1.0"},{"MeasureID":18,"GeoType":"Borough","GeoID":4,"Time":"2003","ban_summary_flag":0,"Value":1.05,"CI":"","Note":"","DisplayValue":"1.0"},{"MeasureID":18,"GeoType":"Borough","GeoID":4,"Time":"2002","ban_summary_flag":0,"Value":1.05,"CI":"","Note":"","DisplayValue":"1.0"},{"MeasureID":18,"GeoType":"Borough","GeoID":4,"Time":"2001","ban_summary_flag":0,"Value":1.07,"CI":"","Note":"","DisplayValue":"1.1"},{"MeasureID":18,"GeoType":"Borough","GeoID":4,"Time":"2000","ban_summary_flag":0,"Value":1.07,"CI":"","Note":"","DisplayValue":"1.1"},{"MeasureID":18,"GeoType":"Borough","GeoID":4,"Time":"1999","ban_summary_flag":0,"Value":1.03,"CI":"","Note":"","DisplayValue":"1.0"},{"MeasureID":18,"GeoType":"Borough","GeoID":4,"Time":"1998","ban_summary_flag":0,"Value":1.04,"CI":"","Note":"","DisplayValue":"1.0"},{"MeasureID":18,"GeoType":"Borough","GeoID":5,"Time":"2013","ban_summary_flag":0,"Value":1.09,"CI":"","Note":"","DisplayValue":"1.1"},{"MeasureID":18,"GeoType":"Borough","GeoID":5,"Time":"2012","ban_summary_flag":0,"Value":1.06,"CI":"","Note":"","DisplayValue":"1.1"},{"MeasureID":18,"GeoType":"Borough","GeoID":5,"Time":"2011","ban_summary_flag":0,"Value":0.99,"CI":"","Note":"","DisplayValue":"1.0"},{"MeasureID":18,"GeoType":"Borough","GeoID":5,"Time":"2010","ban_summary_flag":0,"Value":1.04,"CI":"","Note":"","DisplayValue":"1.0"},{"MeasureID":18,"GeoType":"Borough","GeoID":5,"Time":"2009","ban_summary_flag":0,"Value":1.09,"CI":"","Note":"","DisplayValue":"1.1"},{"MeasureID":18,"GeoType":"Borough","GeoID":5,"Time":"2008","ban_summary_flag":0,"Value":1.08,"CI":"","Note":"","DisplayValue":"1.1"},{"MeasureID":18,"GeoType":"Borough","GeoID":5,"Time":"2007","ban_summary_flag":0,"Value":1.05,"CI":"","Note":"","DisplayValue":"1.0"},{"MeasureID":18,"GeoType":"Borough","GeoID":5,"Time":"2006","ban_summary_flag":0,"Value":1.06,"CI":"","Note":"","DisplayValue":"1.1"},{"MeasureID":18,"GeoType":"Borough","GeoID":5,"Time":"2005","ban_summary_flag":0,"Value":1.01,"CI":"","Note":"","DisplayValue":"1.0"},{"MeasureID":18,"GeoType":"Borough","GeoID":5,"Time":"2004","ban_summary_flag":0,"Value":1.05,"CI":"","Note":"","DisplayValue":"1.0"},{"MeasureID":18,"GeoType":"Borough","GeoID":5,"Time":"2003","ban_summary_flag":0,"Value":1.07,"CI":"","Note":"","DisplayValue":"1.1"},{"MeasureID":18,"GeoType":"Borough","GeoID":5,"Time":"2002","ban_summary_flag":0,"Value":1.03,"CI":"","Note":"","DisplayValue":"1.0"},{"MeasureID":18,"GeoType":"Borough","GeoID":5,"Time":"2001","ban_summary_flag":0,"Value":1.02,"CI":"","Note":"","DisplayValue":"1.0"},{"MeasureID":18,"GeoType":"Borough","GeoID":5,"Time":"2000","ban_summary_flag":0,"Value":1.03,"CI":"","Note":"","DisplayValue":"1.0"},{"MeasureID":18,"GeoType":"Borough","GeoID":5,"Time":"1999","ban_summary_flag":0,"Value":1.09,"CI":"","Note":"","DisplayValue":"1.1"},{"MeasureID":18,"GeoType":"Borough","GeoID":5,"Time":"1998","ban_summary_flag":0,"Value":1.07,"CI":"","Note":"","DisplayValue":"1.1"},{"MeasureID":18,"GeoType":"Citywide","GeoID":1,"Time":"2013","ban_summary_flag":0,"Value":1.04,"CI":"","Note":"","DisplayValue":"1.0"},{"MeasureID":18,"GeoType":"Citywide","GeoID":1,"Time":"2012","ban_summary_flag":0,"Value":1.05,"CI":"","Note":"","DisplayValue":"1.0"},{"MeasureID":18,"GeoType":"Citywide","GeoID":1,"Time":"2011","ban_summary_flag":0,"Value":1.04,"CI":"","Note":"","DisplayValue":"1.0"},{"MeasureID":18,"GeoType":"Citywide","GeoID":1,"Time":"2010","ban_summary_flag":0,"Value":1.05,"CI":"","Note":"","DisplayValue":"1.0"},{"MeasureID":18,"GeoType":"Citywide","GeoID":1,"Time":"2009","ban_summary_flag":0,"Value":1.05,"CI":"","Note":"","DisplayValue":"1.0"},{"MeasureID":18,"GeoType":"Citywide","GeoID":1,"Time":"2008","ban_summary_flag":0,"Value":1.05,"CI":"","Note":"","DisplayValue":"1.0"},{"MeasureID":18,"GeoType":"Citywide","GeoID":1,"Time":"2007","ban_summary_flag":0,"Value":1.03,"CI":"","Note":"","DisplayValue":"1.0"},{"MeasureID":18,"GeoType":"Citywide","GeoID":1,"Time":"2006","ban_summary_flag":0,"Value":1.04,"CI":"","Note":"","DisplayValue":"1.0"},{"MeasureID":18,"GeoType":"Citywide","GeoID":1,"Time":"2005","ban_summary_flag":0,"Value":1.04,"CI":"","Note":"","DisplayValue":"1.0"},{"MeasureID":18,"GeoType":"Citywide","GeoID":1,"Time":"2004","ban_summary_flag":0,"Value":1.04,"CI":"","Note":"","DisplayValue":"1.0"},{"MeasureID":18,"GeoType":"Citywide","GeoID":1,"Time":"2003","ban_summary_flag":0,"Value":1.05,"CI":"","Note":"","DisplayValue":"1.0"},{"MeasureID":18,"GeoType":"Citywide","GeoID":1,"Time":"2002","ban_summary_flag":0,"Value":1.04,"CI":"","Note":"","DisplayValue":"1.0"},{"MeasureID":18,"GeoType":"Citywide","GeoID":1,"Time":"2001","ban_summary_flag":0,"Value":1.05,"CI":"","Note":"","DisplayValue":"1.0"},{"MeasureID":18,"GeoType":"Citywide","GeoID":1,"Time":"2000","ban_summary_flag":0,"Value":1.05,"CI":"","Note":"","DisplayValue":"1.0"},{"MeasureID":18,"GeoType":"Citywide","GeoID":1,"Time":"1999","ban_summary_flag":0,"Value":1.04,"CI":"","Note":"","DisplayValue":"1.0"},{"MeasureID":18,"GeoType":"Citywide","GeoID":1,"Time":"1998","ban_summary_flag":0,"Value":1.05,"CI":"","Note":"","DisplayValue":"1.0"}]
