[{"MeasureID":1006,"GeoType":"Borough","GeoID":1,"Time":"2020","ban_summary_flag":0,"Value":2,"CI":"","Note":"","DisplayValue":"2"},{"MeasureID":1006,"GeoType":"Borough","GeoID":1,"Time":"2019","ban_summary_flag":0,"Value":7,"CI":"","Note":"","DisplayValue":"7"},{"MeasureID":1006,"GeoType":"Borough","GeoID":1,"Time":"2018","ban_summary_flag":0,"Value":10,"CI":"","Note":"","DisplayValue":"10"},{"MeasureID":1006,"GeoType":"Borough","GeoID":1,"Time":"2017","ban_summary_flag":0,"Value":12,"CI":"","Note":"","DisplayValue":"12"},{"MeasureID":1006,"GeoType":"Borough","GeoID":1,"Time":"2016","ban_summary_flag":0,"Value":5,"CI":"","Note":"","DisplayValue":"5"},{"MeasureID":1006,"GeoType":"Borough","GeoID":1,"Time":"2015","ban_summary_flag":0,"Value":4,"CI":"","Note":"","DisplayValue":"4"},{"MeasureID":1006,"GeoType":"Borough","GeoID":1,"Time":"2014","ban_summary_flag":0,"Value":7,"CI":"","Note":"","DisplayValue":"7"},{"MeasureID":1006,"GeoType":"Borough","GeoID":1,"Time":"2013","ban_summary_flag":0,"Value":12,"CI":"","Note":"","DisplayValue":"12"},{"MeasureID":1006,"GeoType":"Borough","GeoID":1,"Time":"2012","ban_summary_flag":0,"Value":1,"CI":"","Note":"","DisplayValue":"1"},{"MeasureID":1006,"GeoType":"Borough","GeoID":1,"Time":"2011","ban_summary_flag":0,"Value":4,"CI":"","Note":"","DisplayValue":"4"},{"MeasureID":1006,"GeoType":"Borough","GeoID":1,"Time":"2010","ban_summary_flag":0,"Value":1,"CI":"","Note":"","DisplayValue":"1"},{"MeasureID":1006,"GeoType":"Borough","GeoID":1,"Time":"2009","ban_summary_flag":0,"Value":5,"CI":"","Note":"","DisplayValue":"5"},{"MeasureID":1006,"GeoType":"Borough","GeoID":1,"Time":"2008","ban_summary_flag":0,"Value":3,"CI":"","Note":"","DisplayValue":"3"},{"MeasureID":1006,"GeoType":"Borough","GeoID":1,"Time":"2007","ban_summary_flag":0,"Value":5,"CI":"","Note":"","DisplayValue":"5"},{"MeasureID":1006,"GeoType":"Borough","GeoID":1,"Time":"2006","ban_summary_flag":0,"Value":1,"CI":"","Note":"","DisplayValue":"1"},{"MeasureID":1006,"GeoType":"Borough","GeoID":1,"Time":"2005","ban_summary_flag":0,"Value":0,"CI":"","Note":"","DisplayValue":"0"},{"MeasureID":1006,"GeoType":"Borough","GeoID":1,"Time":"2004","ban_summary_flag":0,"Value":0,"CI":"","Note":"","DisplayValue":"0"},{"MeasureID":1006,"GeoType":"Borough","GeoID":1,"Time":"2003","ban_summary_flag":0,"Value":0,"CI":"","Note":"","DisplayValue":"0"},{"MeasureID":1006,"GeoType":"Borough","GeoID":1,"Time":"2002","ban_summary_flag":0,"Value":0,"CI":"","Note":"","DisplayValue":"0"},{"MeasureID":1006,"GeoType":"Borough","GeoID":1,"Time":"2001","ban_summary_flag":0,"Value":0,"CI":"","Note":"","DisplayValue":"0"},{"MeasureID":1006,"GeoType":"Borough","GeoID":1,"Time":"2000","ban_summary_flag":0,"Value":0,"CI":"","Note":"","DisplayValue":"0"},{"MeasureID":1006,"GeoType":"Borough","GeoID":2,"Time":"2020","ban_summary_flag":0,"Value":13,"CI":"","Note":"","DisplayValue":"13"},{"MeasureID":1006,"GeoType":"Borough","GeoID":2,"Time":"2019","ban_summary_flag":0,"Value":13,"CI":"","Note":"","DisplayValue":"13"},{"MeasureID":1006,"GeoType":"Borough","GeoID":2,"Time":"2018","ban_summary_flag":0,"Value":11,"CI":"","Note":"","DisplayValue":"11"},{"MeasureID":1006,"GeoType":"Borough","GeoID":2,"Time":"2017","ban_summary_flag":0,"Value":19,"CI":"","Note":"","DisplayValue":"19"},{"MeasureID":1006,"GeoType":"Borough","GeoID":2,"Time":"2016","ban_summary_flag":0,"Value":9,"CI":"","Note":"","DisplayValue":"9"},{"MeasureID":1006,"GeoType":"Borough","GeoID":2,"Time":"2015","ban_summary_flag":0,"Value":8,"CI":"","Note":"","DisplayValue":"8"},{"MeasureID":1006,"GeoType":"Borough","GeoID":2,"Time":"2014","ban_summary_flag":0,"Value":6,"CI":"","Note":"","DisplayValue":"6"},{"MeasureID":1006,"GeoType":"Borough","GeoID":2,"Time":"2013","ban_summary_flag":0,"Value":5,"CI":"","Note":"","DisplayValue":"5"},{"MeasureID":1006,"GeoType":"Borough","GeoID":2,"Time":"2012","ban_summary_flag":0,"Value":5,"CI":"","Note":"","DisplayValue":"5"},{"MeasureID":1006,"GeoType":"Borough","GeoID":2,"Time":"2011","ban_summary_flag":0,"Value":10,"CI":"","Note":"","DisplayValue":"10"},{"MeasureID":1006,"GeoType":"Borough","GeoID":2,"Time":"2010","ban_summary_flag":0,"Value":5,"CI":"","Note":"","DisplayValue":"5"},{"MeasureID":1006,"GeoType":"Borough","GeoID":2,"Time":"2009","ban_summary_flag":0,"Value":6,"CI":"","Note":"","DisplayValue":"6"},{"MeasureID":1006,"GeoType":"Borough","GeoID":2,"Time":"2008","ban_summary_flag":0,"Value":3,"CI":"","Note":"","DisplayValue":"3"},{"MeasureID":1006,"GeoType":"Borough","GeoID":2,"Time":"2007","ban_summary_flag":0,"Value":3,"CI":"","Note":"","DisplayValue":"3"},{"MeasureID":1006,"GeoType":"Borough","GeoID":2,"Time":"2006","ban_summary_flag":0,"Value":6,"CI":"","Note":"","DisplayValue":"6"},{"MeasureID":1006,"GeoType":"Borough","GeoID":2,"Time":"2005","ban_summary_flag":0,"Value":1,"CI":"","Note":"","DisplayValue":"1"},{"MeasureID":1006,"GeoType":"Borough","GeoID":2,"Time":"2004","ban_summary_flag":0,"Value":2,"CI":"","Note":"","DisplayValue":"2"},{"MeasureID":1006,"GeoType":"Borough","GeoID":2,"Time":"2003","ban_summary_flag":0,"Value":0,"CI":"","Note":"","DisplayValue":"0"},{"MeasureID":1006,"GeoType":"Borough","GeoID":2,"Time":"2002","ban_summary_flag":0,"Value":2,"CI":"","Note":"","DisplayValue":"2"},{"MeasureID":1006,"GeoType":"Borough","GeoID":2,"Time":"2001","ban_summary_flag":0,"Value":1,"CI":"","Note":"","DisplayValue":"1"},{"MeasureID":1006,"GeoType":"Borough","GeoID":2,"Time":"2000","ban_summary_flag":0,"Value":0,"CI":"","Note":"","DisplayValue":"0"},{"MeasureID":1006,"GeoType":"Borough","GeoID":3,"Time":"2020","ban_summary_flag":0,"Value":49,"CI":"","Note":"","DisplayValue":"49"},{"MeasureID":1006,"GeoType":"Borough","GeoID":3,"Time":"2019","ban_summary_flag":0,"Value":41,"CI":"","Note":"","DisplayValue":"41"},{"MeasureID":1006,"GeoType":"Borough","GeoID":3,"Time":"2018","ban_summary_flag":0,"Value":38,"CI":"","Note":"","DisplayValue":"38"},{"MeasureID":1006,"GeoType":"Borough","GeoID":3,"Time":"2017","ban_summary_flag":0,"Value":41,"CI":"","Note":"","DisplayValue":"41"},{"MeasureID":1006,"GeoType":"Borough","GeoID":3,"Time":"2016","ban_summary_flag":0,"Value":23,"CI":"","Note":"","DisplayValue":"23"},{"MeasureID":1006,"GeoType":"Borough","GeoID":3,"Time":"2015","ban_summary_flag":0,"Value":39,"CI":"","Note":"","DisplayValue":"39"},{"MeasureID":1006,"GeoType":"Borough","GeoID":3,"Time":"2014","ban_summary_flag":0,"Value":24,"CI":"","Note":"","DisplayValue":"24"},{"MeasureID":1006,"GeoType":"Borough","GeoID":3,"Time":"2013","ban_summary_flag":0,"Value":45,"CI":"","Note":"","DisplayValue":"45"},{"MeasureID":1006,"GeoType":"Borough","GeoID":3,"Time":"2012","ban_summary_flag":0,"Value":16,"CI":"","Note":"","DisplayValue":"16"},{"MeasureID":1006,"GeoType":"Borough","GeoID":3,"Time":"2011","ban_summary_flag":0,"Value":28,"CI":"","Note":"","DisplayValue":"28"},{"MeasureID":1006,"GeoType":"Borough","GeoID":3,"Time":"2010","ban_summary_flag":0,"Value":21,"CI":"","Note":"","DisplayValue":"21"},{"MeasureID":1006,"GeoType":"Borough","GeoID":3,"Time":"2009","ban_summary_flag":0,"Value":25,"CI":"","Note":"","DisplayValue":"25"},{"MeasureID":1006,"GeoType":"Borough","GeoID":3,"Time":"2008","ban_summary_flag":0,"Value":23,"CI":"","Note":"","DisplayValue":"23"},{"MeasureID":1006,"GeoType":"Borough","GeoID":3,"Time":"2007","ban_summary_flag":0,"Value":14,"CI":"","Note":"","DisplayValue":"14"},{"MeasureID":1006,"GeoType":"Borough","GeoID":3,"Time":"2006","ban_summary_flag":0,"Value":21,"CI":"","Note":"","DisplayValue":"21"},{"MeasureID":1006,"GeoType":"Borough","GeoID":3,"Time":"2005","ban_summary_flag":0,"Value":19,"CI":"","Note":"","DisplayValue":"19"},{"MeasureID":1006,"GeoType":"Borough","GeoID":3,"Time":"2004","ban_summary_flag":0,"Value":13,"CI":"","Note":"","DisplayValue":"13"},{"MeasureID":1006,"GeoType":"Borough","GeoID":3,"Time":"2003","ban_summary_flag":0,"Value":19,"CI":"","Note":"","DisplayValue":"19"},{"MeasureID":1006,"GeoType":"Borough","GeoID":3,"Time":"2002","ban_summary_flag":0,"Value":13,"CI":"","Note":"","DisplayValue":"13"},{"MeasureID":1006,"GeoType":"Borough","GeoID":3,"Time":"2001","ban_summary_flag":0,"Value":9,"CI":"","Note":"","DisplayValue":"9"},{"MeasureID":1006,"GeoType":"Borough","GeoID":3,"Time":"2000","ban_summary_flag":0,"Value":7,"CI":"","Note":"","DisplayValue":"7"},{"MeasureID":1006,"GeoType":"Borough","GeoID":4,"Time":"2020","ban_summary_flag":0,"Value":11,"CI":"","Note":"","DisplayValue":"11"},{"MeasureID":1006,"GeoType":"Borough","GeoID":4,"Time":"2019","ban_summary_flag":0,"Value":14,"CI":"","Note":"","DisplayValue":"14"},{"MeasureID":1006,"GeoType":"Borough","GeoID":4,"Time":"2018","ban_summary_flag":0,"Value":11,"CI":"","Note":"","DisplayValue":"11"},{"MeasureID":1006,"GeoType":"Borough","GeoID":4,"Time":"2017","ban_summary_flag":0,"Value":10,"CI":"","Note":"","DisplayValue":"10"},{"MeasureID":1006,"GeoType":"Borough","GeoID":4,"Time":"2016","ban_summary_flag":0,"Value":11,"CI":"","Note":"","DisplayValue":"11"},{"MeasureID":1006,"GeoType":"Borough","GeoID":4,"Time":"2015","ban_summary_flag":0,"Value":16,"CI":"","Note":"","DisplayValue":"16"},{"MeasureID":1006,"GeoType":"Borough","GeoID":4,"Time":"2014","ban_summary_flag":0,"Value":12,"CI":"","Note":"","DisplayValue":"12"},{"MeasureID":1006,"GeoType":"Borough","GeoID":4,"Time":"2013","ban_summary_flag":0,"Value":12,"CI":"","Note":"","DisplayValue":"12"},{"MeasureID":1006,"GeoType":"Borough","GeoID":4,"Time":"2012","ban_summary_flag":0,"Value":6,"CI":"","Note":"","DisplayValue":"6"},{"MeasureID":1006,"GeoType":"Borough","GeoID":4,"Time":"2011","ban_summary_flag":0,"Value":14,"CI":"","Note":"","DisplayValue":"14"},{"MeasureID":1006,"GeoType":"Borough","GeoID":4,"Time":"2010","ban_summary_flag":0,"Value":9,"CI":"","Note":"","DisplayValue":"9"},{"MeasureID":1006,"GeoType":"Borough","GeoID":4,"Time":"2009","ban_summary_flag":0,"Value":6,"CI":"","Note":"","DisplayValue":"6"},{"MeasureID":1006,"GeoType":"Borough","GeoID":4,"Time":"2008","ban_summary_flag":0,"Value":9,"CI":"","Note":"","DisplayValue":"9"},{"MeasureID":1006,"GeoType":"Borough","GeoID":4,"Time":"2007","ban_summary_flag":0,"Value":3,"CI":"","Note":"","DisplayValue":"3"},{"MeasureID":1006,"GeoType":"Borough","GeoID":4,"Time":"2006","ban_summary_flag":0,"Value":8,"CI":"","Note":"","DisplayValue":"8"},{"MeasureID":1006,"GeoType":"Borough","GeoID":4,"Time":"2005","ban_summary_flag":0,"Value":1,"CI":"","Note":"","DisplayValue":"1"},{"MeasureID":1006,"GeoType":"Borough","GeoID":4,"Time":"2004","ban_summary_flag":0,"Value":2,"CI":"","Note":"","DisplayValue":"2"},{"MeasureID":1006,"GeoType":"Borough","GeoID":4,"Time":"2003","ban_summary_flag":0,"Value":5,"CI":"","Note":"","DisplayValue":"5"},{"MeasureID":1006,"GeoType":"Borough","GeoID":4,"Time":"2002","ban_summary_flag":0,"Value":1,"CI":"","Note":"","DisplayValue":"1"},{"MeasureID":1006,"GeoType":"Borough","GeoID":4,"Time":"2001","ban_summary_flag":0,"Value":9,"CI":"","Note":"","DisplayValue":"9"},{"MeasureID":1006,"GeoType":"Borough","GeoID":4,"Time":"2000","ban_summary_flag":0,"Value":3,"CI":"","Note":"","DisplayValue":"3"},{"MeasureID":1006,"GeoType":"Borough","GeoID":5,"Time":"2020","ban_summary_flag":0,"Value":11,"CI":"","Note":"","DisplayValue":"11"},{"MeasureID":1006,"GeoType":"Borough","GeoID":5,"Time":"2019","ban_summary_flag":0,"Value":8,"CI":"","Note":"","DisplayValue":"8"},{"MeasureID":1006,"GeoType":"Borough","GeoID":5,"Time":"2018","ban_summary_flag":0,"Value":13,"CI":"","Note":"","DisplayValue":"13"},{"MeasureID":1006,"GeoType":"Borough","GeoID":5,"Time":"2017","ban_summary_flag":0,"Value":8,"CI":"","Note":"","DisplayValue":"8"},{"MeasureID":1006,"GeoType":"Borough","GeoID":5,"Time":"2016","ban_summary_flag":0,"Value":3,"CI":"","Note":"","DisplayValue":"3"},{"MeasureID":1006,"GeoType":"Borough","GeoID":5,"Time":"2015","ban_summary_flag":0,"Value":2,"CI":"","Note":"","DisplayValue":"2"},{"MeasureID":1006,"GeoType":"Borough","GeoID":5,"Time":"2014","ban_summary_flag":0,"Value":1,"CI":"","Note":"","DisplayValue":"1"},{"MeasureID":1006,"GeoType":"Borough","GeoID":5,"Time":"2013","ban_summary_flag":0,"Value":1,"CI":"","Note":"","DisplayValue":"1"},{"MeasureID":1006,"GeoType":"Borough","GeoID":5,"Time":"2012","ban_summary_flag":0,"Value":0,"CI":"","Note":"","DisplayValue":"0"},{"MeasureID":1006,"GeoType":"Borough","GeoID":5,"Time":"2011","ban_summary_flag":0,"Value":1,"CI":"","Note":"","DisplayValue":"1"},{"MeasureID":1006,"GeoType":"Borough","GeoID":5,"Time":"2010","ban_summary_flag":0,"Value":0,"CI":"","Note":"","DisplayValue":"0"},{"MeasureID":1006,"GeoType":"Borough","GeoID":5,"Time":"2009","ban_summary_flag":0,"Value":0,"CI":"","Note":"","DisplayValue":"0"},{"MeasureID":1006,"GeoType":"Borough","GeoID":5,"Time":"2008","ban_summary_flag":0,"Value":1,"CI":"","Note":"","DisplayValue":"1"},{"MeasureID":1006,"GeoType":"Borough","GeoID":5,"Time":"2007","ban_summary_flag":0,"Value":0,"CI":"","Note":"","DisplayValue":"0"},{"MeasureID":1006,"GeoType":"Borough","GeoID":5,"Time":"2006","ban_summary_flag":0,"Value":2,"CI":"","Note":"","DisplayValue":"2"},{"MeasureID":1006,"GeoType":"Borough","GeoID":5,"Time":"2005","ban_summary_flag":0,"Value":0,"CI":"","Note":"","DisplayValue":"0"},{"MeasureID":1006,"GeoType":"Borough","GeoID":5,"Time":"2004","ban_summary_flag":0,"Value":0,"CI":"","Note":"","DisplayValue":"0"},{"MeasureID":1006,"GeoType":"Borough","GeoID":5,"Time":"2003","ban_summary_flag":0,"Value":1,"CI":"","Note":"","DisplayValue":"1"},{"MeasureID":1006,"GeoType":"Borough","GeoID":5,"Time":"2002","ban_summary_flag":0,"Value":0,"CI":"","Note":"","DisplayValue":"0"},{"MeasureID":1006,"GeoType":"Borough","GeoID":5,"Time":"2001","ban_summary_flag":0,"Value":0,"CI":"","Note":"","DisplayValue":"0"},{"MeasureID":1006,"GeoType":"Borough","GeoID":5,"Time":"2000","ban_summary_flag":0,"Value":0,"CI":"","Note":"","DisplayValue":"0"},{"MeasureID":1006,"GeoType":"Citywide","GeoID":1,"Time":"2020","ban_summary_flag":0,"Value":86,"CI":"","Note":"","DisplayValue":"86"},{"MeasureID":1006,"GeoType":"Citywide","GeoID":1,"Time":"2019","ban_summary_flag":0,"Value":83,"CI":"","Note":"","DisplayValue":"83"},{"MeasureID":1006,"GeoType":"Citywide","GeoID":1,"Time":"2018","ban_summary_flag":0,"Value":83,"CI":"","Note":"","DisplayValue":"83"},{"MeasureID":1006,"GeoType":"Citywide","GeoID":1,"Time":"2017","ban_summary_flag":0,"Value":90,"CI":"","Note":"","DisplayValue":"90"},{"MeasureID":1006,"GeoType":"Citywide","GeoID":1,"Time":"2016","ban_summary_flag":0,"Value":51,"CI":"","Note":"","DisplayValue":"51"},{"MeasureID":1006,"GeoType":"Citywide","GeoID":1,"Time":"2015","ban_summary_flag":0,"Value":69,"CI":"","Note":"","DisplayValue":"69"},{"MeasureID":1006,"GeoType":"Citywide","GeoID":1,"Time":"2014","ban_summary_flag":0,"Value":50,"CI":"","Note":"","DisplayValue":"50"},{"MeasureID":1006,"GeoType":"Citywide","GeoID":1,"Time":"2013","ban_summary_flag":0,"Value":75,"CI":"","Note":"","DisplayValue":"75"},{"MeasureID":1006,"GeoType":"Citywide","GeoID":1,"Time":"2012","ban_summary_flag":0,"Value":28,"CI":"","Note":"","DisplayValue":"28"},{"MeasureID":1006,"GeoType":"Citywide","GeoID":1,"Time":"2011","ban_summary_flag":0,"Value":57,"CI":"","Note":"","DisplayValue":"57"},{"MeasureID":1006,"GeoType":"Citywide","GeoID":1,"Time":"2010","ban_summary_flag":0,"Value":36,"CI":"","Note":"","DisplayValue":"36"},{"MeasureID":1006,"GeoType":"Citywide","GeoID":1,"Time":"2009","ban_summary_flag":0,"Value":42,"CI":"","Note":"","DisplayValue":"42"},{"MeasureID":1006,"GeoType":"Citywide","GeoID":1,"Time":"2008","ban_summary_flag":0,"Value":39,"CI":"","Note":"","DisplayValue":"39"},{"MeasureID":1006,"GeoType":"Citywide","GeoID":1,"Time":"2007","ban_summary_flag":0,"Value":25,"CI":"","Note":"","DisplayValue":"25"},{"MeasureID":1006,"GeoType":"Citywide","GeoID":1,"Time":"2006","ban_summary_flag":0,"Value":38,"CI":"","Note":"","DisplayValue":"38"},{"MeasureID":1006,"GeoType":"Citywide","GeoID":1,"Time":"2005","ban_summary_flag":0,"Value":21,"CI":"","Note":"","DisplayValue":"21"},{"MeasureID":1006,"GeoType":"Citywide","GeoID":1,"Time":"2004","ban_summary_flag":0,"Value":17,"CI":"","Note":"","DisplayValue":"17"},{"MeasureID":1006,"GeoType":"Citywide","GeoID":1,"Time":"2003","ban_summary_flag":0,"Value":25,"CI":"","Note":"","DisplayValue":"25"},{"MeasureID":1006,"GeoType":"Citywide","GeoID":1,"Time":"2002","ban_summary_flag":0,"Value":16,"CI":"","Note":"","DisplayValue":"16"},{"MeasureID":1006,"GeoType":"Citywide","GeoID":1,"Time":"2001","ban_summary_flag":0,"Value":19,"CI":"","Note":"","DisplayValue":"19"},{"MeasureID":1006,"GeoType":"Citywide","GeoID":1,"Time":"2000","ban_summary_flag":0,"Value":10,"CI":"","Note":"","DisplayValue":"10"},{"MeasureID":1007,"GeoType":"Borough","GeoID":1,"Time":"2020","ban_summary_flag":0,"Value":0.1,"CI":"","Note":"","DisplayValue":"0.1"},{"MeasureID":1007,"GeoType":"Borough","GeoID":1,"Time":"2019","ban_summary_flag":0,"Value":0.5,"CI":"","Note":"","DisplayValue":"0.5"},{"MeasureID":1007,"GeoType":"Borough","GeoID":1,"Time":"2018","ban_summary_flag":0,"Value":0.7,"CI":"","Note":"","DisplayValue":"0.7"},{"MeasureID":1007,"GeoType":"Borough","GeoID":1,"Time":"2017","ban_summary_flag":0,"Value":0.8,"CI":"","Note":"","DisplayValue":"0.8"},{"MeasureID":1007,"GeoType":"Borough","GeoID":1,"Time":"2016","ban_summary_flag":0,"Value":0.3,"CI":"","Note":"","DisplayValue":"0.3"},{"MeasureID":1007,"GeoType":"Borough","GeoID":1,"Time":"2015","ban_summary_flag":0,"Value":0.3,"CI":"","Note":"","DisplayValue":"0.3"},{"MeasureID":1007,"GeoType":"Borough","GeoID":1,"Time":"2014","ban_summary_flag":0,"Value":0.5,"CI":"","Note":"","DisplayValue":"0.5"},{"MeasureID":1007,"GeoType":"Borough","GeoID":1,"Time":"2013","ban_summary_flag":0,"Value":0.8,"CI":"","Note":"","DisplayValue":"0.8"},{"MeasureID":1007,"GeoType":"Borough","GeoID":1,"Time":"2012","ban_summary_flag":0,"Value":0.1,"CI":"","Note":"","DisplayValue":"0.1"},{"MeasureID":1007,"GeoType":"Borough","GeoID":1,"Time":"2011","ban_summary_flag":0,"Value":0.3,"CI":"","Note":"","DisplayValue":"0.3"},{"MeasureID":1007,"GeoType":"Borough","GeoID":1,"Time":"2010","ban_summary_flag":0,"Value":0.1,"CI":"","Note":"","DisplayValue":"0.1"},{"MeasureID":1007,"GeoType":"Borough","GeoID":1,"Time":"2009","ban_summary_flag":0,"Value":0.4,"CI":"","Note":"","DisplayValue":"0.4"},{"MeasureID":1007,"GeoType":"Borough","GeoID":1,"Time":"2008","ban_summary_flag":0,"Value":0.2,"CI":"","Note":"","DisplayValue":"0.2"},{"MeasureID":1007,"GeoType":"Borough","GeoID":1,"Time":"2007","ban_summary_flag":0,"Value":0.4,"CI":"","Note":"","DisplayValue":"0.4"},{"MeasureID":1007,"GeoType":"Borough","GeoID":1,"Time":"2006","ban_summary_flag":0,"Value":0.1,"CI":"","Note":"","DisplayValue":"0.1"},{"MeasureID":1007,"GeoType":"Borough","GeoID":1,"Time":"2005","ban_summary_flag":0,"Value":0,"CI":"","Note":"","DisplayValue":"0.0"},{"MeasureID":1007,"GeoType":"Borough","GeoID":1,"Time":"2004","ban_summary_flag":0,"Value":0,"CI":"","Note":"","DisplayValue":"0.0"},{"MeasureID":1007,"GeoType":"Borough","GeoID":1,"Time":"2003","ban_summary_flag":0,"Value":0,"CI":"","Note":"","DisplayValue":"0.0"},{"MeasureID":1007,"GeoType":"Borough","GeoID":1,"Time":"2002","ban_summary_flag":0,"Value":0,"CI":"","Note":"","DisplayValue":"0.0"},{"MeasureID":1007,"GeoType":"Borough","GeoID":1,"Time":"2001","ban_summary_flag":0,"Value":0,"CI":"","Note":"","DisplayValue":"0.0"},{"MeasureID":1007,"GeoType":"Borough","GeoID":1,"Time":"2000","ban_summary_flag":0,"Value":0,"CI":"","Note":"","DisplayValue":"0.0"},{"MeasureID":1007,"GeoType":"Borough","GeoID":2,"Time":"2020","ban_summary_flag":0,"Value":0.5,"CI":"","Note":"","DisplayValue":"0.5"},{"MeasureID":1007,"GeoType":"Borough","GeoID":2,"Time":"2019","ban_summary_flag":0,"Value":0.5,"CI":"","Note":"","DisplayValue":"0.5"},{"MeasureID":1007,"GeoType":"Borough","GeoID":2,"Time":"2018","ban_summary_flag":0,"Value":0.4,"CI":"","Note":"","DisplayValue":"0.4"},{"MeasureID":1007,"GeoType":"Borough","GeoID":2,"Time":"2017","ban_summary_flag":0,"Value":0.7,"CI":"","Note":"","DisplayValue":"0.7"},{"MeasureID":1007,"GeoType":"Borough","GeoID":2,"Time":"2016","ban_summary_flag":0,"Value":0.3,"CI":"","Note":"","DisplayValue":"0.3"},{"MeasureID":1007,"GeoType":"Borough","GeoID":2,"Time":"2015","ban_summary_flag":0,"Value":0.3,"CI":"","Note":"","DisplayValue":"0.3"},{"MeasureID":1007,"GeoType":"Borough","GeoID":2,"Time":"2014","ban_summary_flag":0,"Value":0.2,"CI":"","Note":"","DisplayValue":"0.2"},{"MeasureID":1007,"GeoType":"Borough","GeoID":2,"Time":"2013","ban_summary_flag":0,"Value":0.2,"CI":"","Note":"","DisplayValue":"0.2"},{"MeasureID":1007,"GeoType":"Borough","GeoID":2,"Time":"2012","ban_summary_flag":0,"Value":0.2,"CI":"","Note":"","DisplayValue":"0.2"},{"MeasureID":1007,"GeoType":"Borough","GeoID":2,"Time":"2011","ban_summary_flag":0,"Value":0.4,"CI":"","Note":"","DisplayValue":"0.4"},{"MeasureID":1007,"GeoType":"Borough","GeoID":2,"Time":"2010","ban_summary_flag":0,"Value":0.2,"CI":"","Note":"","DisplayValue":"0.2"},{"MeasureID":1007,"GeoType":"Borough","GeoID":2,"Time":"2009","ban_summary_flag":0,"Value":0.2,"CI":"","Note":"","DisplayValue":"0.2"},{"MeasureID":1007,"GeoType":"Borough","GeoID":2,"Time":"2008","ban_summary_flag":0,"Value":0.1,"CI":"","Note":"","DisplayValue":"0.1"},{"MeasureID":1007,"GeoType":"Borough","GeoID":2,"Time":"2007","ban_summary_flag":0,"Value":0.1,"CI":"","Note":"","DisplayValue":"0.1"},{"MeasureID":1007,"GeoType":"Borough","GeoID":2,"Time":"2006","ban_summary_flag":0,"Value":0.3,"CI":"","Note":"","DisplayValue":"0.3"},{"MeasureID":1007,"GeoType":"Borough","GeoID":2,"Time":"2005","ban_summary_flag":0,"Value":0,"CI":"","Note":"","DisplayValue":"0.0"},{"MeasureID":1007,"GeoType":"Borough","GeoID":2,"Time":"2004","ban_summary_flag":0,"Value":0.1,"CI":"","Note":"","DisplayValue":"0.1"},{"MeasureID":1007,"GeoType":"Borough","GeoID":2,"Time":"2003","ban_summary_flag":0,"Value":0,"CI":"","Note":"","DisplayValue":"0.0"},{"MeasureID":1007,"GeoType":"Borough","GeoID":2,"Time":"2002","ban_summary_flag":0,"Value":0.1,"CI":"","Note":"","DisplayValue":"0.1"},{"MeasureID":1007,"GeoType":"Borough","GeoID":2,"Time":"2001","ban_summary_flag":0,"Value":0,"CI":"","Note":"","DisplayValue":"0.0"},{"MeasureID":1007,"GeoType":"Borough","GeoID":2,"Time":"2000","ban_summary_flag":0,"Value":0,"CI":"","Note":"","DisplayValue":"0.0"},{"MeasureID":1007,"GeoType":"Borough","GeoID":3,"Time":"2020","ban_summary_flag":0,"Value":2.6,"CI":"","Note":"","DisplayValue":"2.6"},{"MeasureID":1007,"GeoType":"Borough","GeoID":3,"Time":"2019","ban_summary_flag":0,"Value":2.1,"CI":"","Note":"","DisplayValue":"2.1"},{"MeasureID":1007,"GeoType":"Borough","GeoID":3,"Time":"2018","ban_summary_flag":0,"Value":1.9,"CI":"","Note":"","DisplayValue":"1.9"},{"MeasureID":1007,"GeoType":"Borough","GeoID":3,"Time":"2017","ban_summary_flag":0,"Value":2.1,"CI":"","Note":"","DisplayValue":"2.1"},{"MeasureID":1007,"GeoType":"Borough","GeoID":3,"Time":"2016","ban_summary_flag":0,"Value":1.2,"CI":"","Note":"","DisplayValue":"1.2"},{"MeasureID":1007,"GeoType":"Borough","GeoID":3,"Time":"2015","ban_summary_flag":0,"Value":2.1,"CI":"","Note":"","DisplayValue":"2.1"},{"MeasureID":1007,"GeoType":"Borough","GeoID":3,"Time":"2014","ban_summary_flag":0,"Value":1.3,"CI":"","Note":"","DisplayValue":"1.3"},{"MeasureID":1007,"GeoType":"Borough","GeoID":3,"Time":"2013","ban_summary_flag":0,"Value":2.5,"CI":"","Note":"","DisplayValue":"2.5"},{"MeasureID":1007,"GeoType":"Borough","GeoID":3,"Time":"2012","ban_summary_flag":0,"Value":0.9,"CI":"","Note":"","DisplayValue":"0.9"},{"MeasureID":1007,"GeoType":"Borough","GeoID":3,"Time":"2011","ban_summary_flag":0,"Value":1.7,"CI":"","Note":"","DisplayValue":"1.7"},{"MeasureID":1007,"GeoType":"Borough","GeoID":3,"Time":"2010","ban_summary_flag":0,"Value":1.2,"CI":"","Note":"","DisplayValue":"1.2"},{"MeasureID":1007,"GeoType":"Borough","GeoID":3,"Time":"2009","ban_summary_flag":0,"Value":1.4,"CI":"","Note":"","DisplayValue":"1.4"},{"MeasureID":1007,"GeoType":"Borough","GeoID":3,"Time":"2008","ban_summary_flag":0,"Value":1.4,"CI":"","Note":"","DisplayValue":"1.4"},{"MeasureID":1007,"GeoType":"Borough","GeoID":3,"Time":"2007","ban_summary_flag":0,"Value":0.8,"CI":"","Note":"","DisplayValue":"0.8"},{"MeasureID":1007,"GeoType":"Borough","GeoID":3,"Time":"2006","ban_summary_flag":0,"Value":1.2,"CI":"","Note":"","DisplayValue":"1.2"},{"MeasureID":1007,"GeoType":"Borough","GeoID":3,"Time":"2005","ban_summary_flag":0,"Value":1.1,"CI":"","Note":"","DisplayValue":"1.1"},{"MeasureID":1007,"GeoType":"Borough","GeoID":3,"Time":"2004","ban_summary_flag":0,"Value":0.8,"CI":"","Note":"","DisplayValue":"0.8"},{"MeasureID":1007,"GeoType":"Borough","GeoID":3,"Time":"2003","ban_summary_flag":0,"Value":1.2,"CI":"","Note":"","DisplayValue":"1.2"},{"MeasureID":1007,"GeoType":"Borough","GeoID":3,"Time":"2002","ban_summary_flag":0,"Value":0.8,"CI":"","Note":"","DisplayValue":"0.8"},{"MeasureID":1007,"GeoType":"Borough","GeoID":3,"Time":"2001","ban_summary_flag":0,"Value":0.5,"CI":"","Note":"","DisplayValue":"0.5"},{"MeasureID":1007,"GeoType":"Borough","GeoID":3,"Time":"2000","ban_summary_flag":0,"Value":0.4,"CI":"","Note":"","DisplayValue":"0.4"},{"MeasureID":1007,"GeoType":"Borough","GeoID":4,"Time":"2020","ban_summary_flag":0,"Value":0.4,"CI":"","Note":"","DisplayValue":"0.4"},{"MeasureID":1007,"GeoType":"Borough","GeoID":4,"Time":"2019","ban_summary_flag":0,"Value":0.5,"CI":"","Note":"","DisplayValue":"0.5"},{"MeasureID":1007,"GeoType":"Borough","GeoID":4,"Time":"2018","ban_summary_flag":0,"Value":0.4,"CI":"","Note":"","DisplayValue":"0.4"},{"MeasureID":1007,"GeoType":"Borough","GeoID":4,"Time":"2017","ban_summary_flag":0,"Value":0.4,"CI":"","Note":"","DisplayValue":"0.4"},{"MeasureID":1007,"GeoType":"Borough","GeoID":4,"Time":"2016","ban_summary_flag":0,"Value":0.4,"CI":"","Note":"","DisplayValue":"0.4"},{"MeasureID":1007,"GeoType":"Borough","GeoID":4,"Time":"2015","ban_summary_flag":0,"Value":0.6,"CI":"","Note":"","DisplayValue":"0.6"},{"MeasureID":1007,"GeoType":"Borough","GeoID":4,"Time":"2014","ban_summary_flag":0,"Value":0.5,"CI":"","Note":"","DisplayValue":"0.5"},{"MeasureID":1007,"GeoType":"Borough","GeoID":4,"Time":"2013","ban_summary_flag":0,"Value":0.5,"CI":"","Note":"","DisplayValue":"0.5"},{"MeasureID":1007,"GeoType":"Borough","GeoID":4,"Time":"2012","ban_summary_flag":0,"Value":0.3,"CI":"","Note":"","DisplayValue":"0.3"},{"MeasureID":1007,"GeoType":"Borough","GeoID":4,"Time":"2011","ban_summary_flag":0,"Value":0.6,"CI":"","Note":"","DisplayValue":"0.6"},{"MeasureID":1007,"GeoType":"Borough","GeoID":4,"Time":"2010","ban_summary_flag":0,"Value":0.4,"CI":"","Note":"","DisplayValue":"0.4"},{"MeasureID":1007,"GeoType":"Borough","GeoID":4,"Time":"2009","ban_summary_flag":0,"Value":0.3,"CI":"","Note":"","DisplayValue":"0.3"},{"MeasureID":1007,"GeoType":"Borough","GeoID":4,"Time":"2008","ban_summary_flag":0,"Value":0.4,"CI":"","Note":"","DisplayValue":"0.4"},{"MeasureID":1007,"GeoType":"Borough","GeoID":4,"Time":"2007","ban_summary_flag":0,"Value":0.1,"CI":"","Note":"","DisplayValue":"0.1"},{"MeasureID":1007,"GeoType":"Borough","GeoID":4,"Time":"2006","ban_summary_flag":0,"Value":0.3,"CI":"","Note":"","DisplayValue":"0.3"},{"MeasureID":1007,"GeoType":"Borough","GeoID":4,"Time":"2005","ban_summary_flag":0,"Value":0,"CI":"","Note":"","DisplayValue":"0.0"},{"MeasureID":1007,"GeoType":"Borough","GeoID":4,"Time":"2004","ban_summary_flag":0,"Value":0.1,"CI":"","Note":"","DisplayValue":"0.1"},{"MeasureID":1007,"GeoType":"Borough","GeoID":4,"Time":"2003","ban_summary_flag":0,"Value":0.2,"CI":"","Note":"","DisplayValue":"0.2"},{"MeasureID":1007,"GeoType":"Borough","GeoID":4,"Time":"2002","ban_summary_flag":0,"Value":0,"CI":"","Note":"","DisplayValue":"0.0"},{"MeasureID":1007,"GeoType":"Borough","GeoID":4,"Time":"2001","ban_summary_flag":0,"Value":0.4,"CI":"","Note":"","DisplayValue":"0.4"},{"MeasureID":1007,"GeoType":"Borough","GeoID":4,"Time":"2000","ban_summary_flag":0,"Value":0.1,"CI":"","Note":"","DisplayValue":"0.1"},{"MeasureID":1007,"GeoType":"Borough","GeoID":5,"Time":"2020","ban_summary_flag":0,"Value":1.9,"CI":"","Note":"","DisplayValue":"1.9"},{"MeasureID":1007,"GeoType":"Borough","GeoID":5,"Time":"2019","ban_summary_flag":0,"Value":1.6,"CI":"","Note":"","DisplayValue":"1.6"},{"MeasureID":1007,"GeoType":"Borough","GeoID":5,"Time":"2018","ban_summary_flag":0,"Value":2.4,"CI":"","Note":"","DisplayValue":"2.4"},{"MeasureID":1007,"GeoType":"Borough","GeoID":5,"Time":"2017","ban_summary_flag":0,"Value":1.3,"CI":"","Note":"","DisplayValue":"1.3"},{"MeasureID":1007,"GeoType":"Borough","GeoID":5,"Time":"2016","ban_summary_flag":0,"Value":0.6,"CI":"","Note":"","DisplayValue":"0.6"},{"MeasureID":1007,"GeoType":"Borough","GeoID":5,"Time":"2015","ban_summary_flag":0,"Value":0.4,"CI":"","Note":"","DisplayValue":"0.4"},{"MeasureID":1007,"GeoType":"Borough","GeoID":5,"Time":"2014","ban_summary_flag":0,"Value":0.2,"CI":"","Note":"","DisplayValue":"0.2"},{"MeasureID":1007,"GeoType":"Borough","GeoID":5,"Time":"2013","ban_summary_flag":0,"Value":0.2,"CI":"","Note":"","DisplayValue":"0.2"},{"MeasureID":1007,"GeoType":"Borough","GeoID":5,"Time":"2012","ban_summary_flag":0,"Value":0,"CI":"","Note":"","DisplayValue":"0.0"},{"MeasureID":1007,"GeoType":"Borough","GeoID":5,"Time":"2011","ban_summary_flag":0,"Value":0.2,"CI":"","Note":"","DisplayValue":"0.2"},{"MeasureID":1007,"GeoType":"Borough","GeoID":5,"Time":"2010","ban_summary_flag":0,"Value":0,"CI":"","Note":"","DisplayValue":"0.0"},{"MeasureID":1007,"GeoType":"Borough","GeoID":5,"Time":"2009","ban_summary_flag":0,"Value":0,"CI":"","Note":"","DisplayValue":"0.0"},{"MeasureID":1007,"GeoType":"Borough","GeoID":5,"Time":"2008","ban_summary_flag":0,"Value":0.2,"CI":"","Note":"","DisplayValue":"0.2"},{"MeasureID":1007,"GeoType":"Borough","GeoID":5,"Time":"2007","ban_summary_flag":0,"Value":0,"CI":"","Note":"","DisplayValue":"0.0"},{"MeasureID":1007,"GeoType":"Borough","GeoID":5,"Time":"2006","ban_summary_flag":0,"Value":0.4,"CI":"","Note":"","DisplayValue":"0.4"},{"MeasureID":1007,"GeoType":"Borough","GeoID":5,"Time":"2005","ban_summary_flag":0,"Value":0,"CI":"","Note":"","DisplayValue":"0.0"},{"MeasureID":1007,"GeoType":"Borough","GeoID":5,"Time":"2004","ban_summary_flag":0,"Value":0,"CI":"","Note":"","DisplayValue":"0.0"},{"MeasureID":1007,"GeoType":"Borough","GeoID":5,"Time":"2003","ban_summary_flag":0,"Value":0.2,"CI":"","Note":"","DisplayValue":"0.2"},{"MeasureID":1007,"GeoType":"Borough","GeoID":5,"Time":"2002","ban_summary_flag":0,"Value":0,"CI":"","Note":"","DisplayValue":"0.0"},{"MeasureID":1007,"GeoType":"Borough","GeoID":5,"Time":"2001","ban_summary_flag":0,"Value":0,"CI":"","Note":"","DisplayValue":"0.0"},{"MeasureID":1007,"GeoType":"Borough","GeoID":5,"Time":"2000","ban_summary_flag":0,"Value":0,"CI":"","Note":"","DisplayValue":"0.0"},{"MeasureID":1007,"GeoType":"Citywide","GeoID":1,"Time":"2020","ban_summary_flag":0,"Value":0.9,"CI":"","Note":"","DisplayValue":"0.9"},{"MeasureID":1007,"GeoType":"Citywide","GeoID":1,"Time":"2019","ban_summary_flag":0,"Value":0.9,"CI":"","Note":"","DisplayValue":"0.9"},{"MeasureID":1007,"GeoType":"Citywide","GeoID":1,"Time":"2018","ban_summary_flag":0,"Value":0.9,"CI":"","Note":"","DisplayValue":"0.9"},{"MeasureID":1007,"GeoType":"Citywide","GeoID":1,"Time":"2017","ban_summary_flag":0,"Value":1,"CI":"","Note":"","DisplayValue":"1.0"},{"MeasureID":1007,"GeoType":"Citywide","GeoID":1,"Time":"2016","ban_summary_flag":0,"Value":0.5,"CI":"","Note":"","DisplayValue":"0.5"},{"MeasureID":1007,"GeoType":"Citywide","GeoID":1,"Time":"2015","ban_summary_flag":0,"Value":0.8,"CI":"","Note":"","DisplayValue":"0.8"},{"MeasureID":1007,"GeoType":"Citywide","GeoID":1,"Time":"2014","ban_summary_flag":0,"Value":0.6,"CI":"","Note":"","DisplayValue":"0.6"},{"MeasureID":1007,"GeoType":"Citywide","GeoID":1,"Time":"2013","ban_summary_flag":0,"Value":0.9,"CI":"","Note":"","DisplayValue":"0.9"},{"MeasureID":1007,"GeoType":"Citywide","GeoID":1,"Time":"2012","ban_summary_flag":0,"Value":0.3,"CI":"","Note":"","DisplayValue":"0.3"},{"MeasureID":1007,"GeoType":"Citywide","GeoID":1,"Time":"2011","ban_summary_flag":0,"Value":0.7,"CI":"","Note":"","DisplayValue":"0.7"},{"MeasureID":1007,"GeoType":"Citywide","GeoID":1,"Time":"2010","ban_summary_flag":0,"Value":0.4,"CI":"","Note":"","DisplayValue":"0.4"},{"MeasureID":1007,"GeoType":"Citywide","GeoID":1,"Time":"2009","ban_summary_flag":0,"Value":0.5,"CI":"","Note":"","DisplayValue":"0.5"},{"MeasureID":1007,"GeoType":"Citywide","GeoID":1,"Time":"2008","ban_summary_flag":0,"Value":0.5,"CI":"","Note":"","DisplayValue":"0.5"},{"MeasureID":1007,"GeoType":"Citywide","GeoID":1,"Time":"2007","ban_summary_flag":0,"Value":0.3,"CI":"","Note":"","DisplayValue":"0.3"},{"MeasureID":1007,"GeoType":"Citywide","GeoID":1,"Time":"2006","ban_summary_flag":0,"Value":0.5,"CI":"","Note":"","DisplayValue":"0.5"},{"MeasureID":1007,"GeoType":"Citywide","GeoID":1,"Time":"2005","ban_summary_flag":0,"Value":0.3,"CI":"","Note":"","DisplayValue":"0.3"},{"MeasureID":1007,"GeoType":"Citywide","GeoID":1,"Time":"2004","ban_summary_flag":0,"Value":0.2,"CI":"","Note":"","DisplayValue":"0.2"},{"MeasureID":1007,"GeoType":"Citywide","GeoID":1,"Time":"2003","ban_summary_flag":0,"Value":0.3,"CI":"","Note":"","DisplayValue":"0.3"},{"MeasureID":1007,"GeoType":"Citywide","GeoID":1,"Time":"2002","ban_summary_flag":0,"Value":0.2,"CI":"","Note":"","DisplayValue":"0.2"},{"MeasureID":1007,"GeoType":"Citywide","GeoID":1,"Time":"2001","ban_summary_flag":0,"Value":0.2,"CI":"","Note":"","DisplayValue":"0.2"},{"MeasureID":1007,"GeoType":"Citywide","GeoID":1,"Time":"2000","ban_summary_flag":0,"Value":0.1,"CI":"","Note":"","DisplayValue":"0.1"},{"MeasureID":1008,"GeoType":"Borough","GeoID":1,"Time":"2020","ban_summary_flag":0,"Value":0.1,"CI":"","Note":"","DisplayValue":"0.1"},{"MeasureID":1008,"GeoType":"Borough","GeoID":1,"Time":"2019","ban_summary_flag":0,"Value":0.5,"CI":"","Note":"","DisplayValue":"0.5"},{"MeasureID":1008,"GeoType":"Borough","GeoID":1,"Time":"2018","ban_summary_flag":0,"Value":0.7,"CI":"","Note":"","DisplayValue":"0.7"},{"MeasureID":1008,"GeoType":"Borough","GeoID":1,"Time":"2017","ban_summary_flag":0,"Value":0.8,"CI":"","Note":"","DisplayValue":"0.8"},{"MeasureID":1008,"GeoType":"Borough","GeoID":1,"Time":"2016","ban_summary_flag":0,"Value":0.3,"CI":"","Note":"","DisplayValue":"0.3"},{"MeasureID":1008,"GeoType":"Borough","GeoID":1,"Time":"2015","ban_summary_flag":0,"Value":0.3,"CI":"","Note":"","DisplayValue":"0.3"},{"MeasureID":1008,"GeoType":"Borough","GeoID":1,"Time":"2014","ban_summary_flag":0,"Value":0.5,"CI":"","Note":"","DisplayValue":"0.5"},{"MeasureID":1008,"GeoType":"Borough","GeoID":1,"Time":"2013","ban_summary_flag":0,"Value":0.8,"CI":"","Note":"","DisplayValue":"0.8"},{"MeasureID":1008,"GeoType":"Borough","GeoID":1,"Time":"2012","ban_summary_flag":0,"Value":0.1,"CI":"","Note":"","DisplayValue":"0.1"},{"MeasureID":1008,"GeoType":"Borough","GeoID":1,"Time":"2011","ban_summary_flag":0,"Value":0.3,"CI":"","Note":"","DisplayValue":"0.3"},{"MeasureID":1008,"GeoType":"Borough","GeoID":1,"Time":"2010","ban_summary_flag":0,"Value":0.1,"CI":"","Note":"","DisplayValue":"0.1"},{"MeasureID":1008,"GeoType":"Borough","GeoID":1,"Time":"2009","ban_summary_flag":0,"Value":0.4,"CI":"","Note":"","DisplayValue":"0.4"},{"MeasureID":1008,"GeoType":"Borough","GeoID":1,"Time":"2008","ban_summary_flag":0,"Value":0.2,"CI":"","Note":"","DisplayValue":"0.2"},{"MeasureID":1008,"GeoType":"Borough","GeoID":1,"Time":"2007","ban_summary_flag":0,"Value":0.4,"CI":"","Note":"","DisplayValue":"0.4"},{"MeasureID":1008,"GeoType":"Borough","GeoID":1,"Time":"2006","ban_summary_flag":0,"Value":0.1,"CI":"","Note":"","DisplayValue":"0.1"},{"MeasureID":1008,"GeoType":"Borough","GeoID":1,"Time":"2005","ban_summary_flag":0,"Value":0,"CI":"","Note":"","DisplayValue":"0.0"},{"MeasureID":1008,"GeoType":"Borough","GeoID":1,"Time":"2004","ban_summary_flag":0,"Value":0,"CI":"","Note":"","DisplayValue":"0.0"},{"MeasureID":1008,"GeoType":"Borough","GeoID":1,"Time":"2003","ban_summary_flag":0,"Value":0,"CI":"","Note":"","DisplayValue":"0.0"},{"MeasureID":1008,"GeoType":"Borough","GeoID":1,"Time":"2002","ban_summary_flag":0,"Value":0,"CI":"","Note":"","DisplayValue":"0.0"},{"MeasureID":1008,"GeoType":"Borough","GeoID":1,"Time":"2001","ban_summary_flag":0,"Value":0,"CI":"","Note":"","DisplayValue":"0.0"},{"MeasureID":1008,"GeoType":"Borough","GeoID":1,"Time":"2000","ban_summary_flag":0,"Value":0,"CI":"","Note":"","DisplayValue":"0.0"},{"MeasureID":1008,"GeoType":"Borough","GeoID":2,"Time":"2020","ban_summary_flag":0,"Value":0.5,"CI":"","Note":"","DisplayValue":"0.5"},{"MeasureID":1008,"GeoType":"Borough","GeoID":2,"Time":"2019","ban_summary_flag":0,"Value":0.5,"CI":"","Note":"","DisplayValue":"0.5"},{"MeasureID":1008,"GeoType":"Borough","GeoID":2,"Time":"2018","ban_summary_flag":0,"Value":0.4,"CI":"","Note":"","DisplayValue":"0.4"},{"MeasureID":1008,"GeoType":"Borough","GeoID":2,"Time":"2017","ban_summary_flag":0,"Value":0.7,"CI":"","Note":"","DisplayValue":"0.7"},{"MeasureID":1008,"GeoType":"Borough","GeoID":2,"Time":"2016","ban_summary_flag":0,"Value":0.3,"CI":"","Note":"","DisplayValue":"0.3"},{"MeasureID":1008,"GeoType":"Borough","GeoID":2,"Time":"2015","ban_summary_flag":0,"Value":0.3,"CI":"","Note":"","DisplayValue":"0.3"},{"MeasureID":1008,"GeoType":"Borough","GeoID":2,"Time":"2014","ban_summary_flag":0,"Value":0.2,"CI":"","Note":"","DisplayValue":"0.2"},{"MeasureID":1008,"GeoType":"Borough","GeoID":2,"Time":"2013","ban_summary_flag":0,"Value":0.2,"CI":"","Note":"","DisplayValue":"0.2"},{"MeasureID":1008,"GeoType":"Borough","GeoID":2,"Time":"2012","ban_summary_flag":0,"Value":0.2,"CI":"","Note":"","DisplayValue":"0.2"},{"MeasureID":1008,"GeoType":"Borough","GeoID":2,"Time":"2011","ban_summary_flag":0,"Value":0.4,"CI":"","Note":"","DisplayValue":"0.4"},{"MeasureID":1008,"GeoType":"Borough","GeoID":2,"Time":"2010","ban_summary_flag":0,"Value":0.2,"CI":"","Note":"","DisplayValue":"0.2"},{"MeasureID":1008,"GeoType":"Borough","GeoID":2,"Time":"2009","ban_summary_flag":0,"Value":0.2,"CI":"","Note":"","DisplayValue":"0.2"},{"MeasureID":1008,"GeoType":"Borough","GeoID":2,"Time":"2008","ban_summary_flag":0,"Value":0.1,"CI":"","Note":"","DisplayValue":"0.1"},{"MeasureID":1008,"GeoType":"Borough","GeoID":2,"Time":"2007","ban_summary_flag":0,"Value":0.1,"CI":"","Note":"","DisplayValue":"0.1"},{"MeasureID":1008,"GeoType":"Borough","GeoID":2,"Time":"2006","ban_summary_flag":0,"Value":0.2,"CI":"","Note":"","DisplayValue":"0.2"},{"MeasureID":1008,"GeoType":"Borough","GeoID":2,"Time":"2005","ban_summary_flag":0,"Value":0,"CI":"","Note":"","DisplayValue":"0.0"},{"MeasureID":1008,"GeoType":"Borough","GeoID":2,"Time":"2004","ban_summary_flag":0,"Value":0.1,"CI":"","Note":"","DisplayValue":"0.1"},{"MeasureID":1008,"GeoType":"Borough","GeoID":2,"Time":"2003","ban_summary_flag":0,"Value":0,"CI":"","Note":"","DisplayValue":"0.0"},{"MeasureID":1008,"GeoType":"Borough","GeoID":2,"Time":"2002","ban_summary_flag":0,"Value":0.1,"CI":"","Note":"","DisplayValue":"0.1"},{"MeasureID":1008,"GeoType":"Borough","GeoID":2,"Time":"2001","ban_summary_flag":0,"Value":0,"CI":"","Note":"","DisplayValue":"0.0"},{"MeasureID":1008,"GeoType":"Borough","GeoID":2,"Time":"2000","ban_summary_flag":0,"Value":0,"CI":"","Note":"","DisplayValue":"0.0"},{"MeasureID":1008,"GeoType":"Borough","GeoID":3,"Time":"2020","ban_summary_flag":0,"Value":3,"CI":"","Note":"","DisplayValue":"3.0"},{"MeasureID":1008,"GeoType":"Borough","GeoID":3,"Time":"2019","ban_summary_flag":0,"Value":2.5,"CI":"","Note":"","DisplayValue":"2.5"},{"MeasureID":1008,"GeoType":"Borough","GeoID":3,"Time":"2018","ban_summary_flag":0,"Value":2.3,"CI":"","Note":"","DisplayValue":"2.3"},{"MeasureID":1008,"GeoType":"Borough","GeoID":3,"Time":"2017","ban_summary_flag":0,"Value":2.5,"CI":"","Note":"","DisplayValue":"2.5"},{"MeasureID":1008,"GeoType":"Borough","GeoID":3,"Time":"2016","ban_summary_flag":0,"Value":1.4,"CI":"","Note":"","DisplayValue":"1.4"},{"MeasureID":1008,"GeoType":"Borough","GeoID":3,"Time":"2015","ban_summary_flag":0,"Value":2.4,"CI":"","Note":"","DisplayValue":"2.4"},{"MeasureID":1008,"GeoType":"Borough","GeoID":3,"Time":"2014","ban_summary_flag":0,"Value":1.5,"CI":"","Note":"","DisplayValue":"1.5"},{"MeasureID":1008,"GeoType":"Borough","GeoID":3,"Time":"2013","ban_summary_flag":0,"Value":2.8,"CI":"","Note":"","DisplayValue":"2.8"},{"MeasureID":1008,"GeoType":"Borough","GeoID":3,"Time":"2012","ban_summary_flag":0,"Value":1,"CI":"","Note":"","DisplayValue":"1.0"},{"MeasureID":1008,"GeoType":"Borough","GeoID":3,"Time":"2011","ban_summary_flag":0,"Value":1.7,"CI":"","Note":"","DisplayValue":"1.7"},{"MeasureID":1008,"GeoType":"Borough","GeoID":3,"Time":"2010","ban_summary_flag":0,"Value":1.3,"CI":"","Note":"","DisplayValue":"1.3"},{"MeasureID":1008,"GeoType":"Borough","GeoID":3,"Time":"2009","ban_summary_flag":0,"Value":1.6,"CI":"","Note":"","DisplayValue":"1.6"},{"MeasureID":1008,"GeoType":"Borough","GeoID":3,"Time":"2008","ban_summary_flag":0,"Value":1.4,"CI":"","Note":"","DisplayValue":"1.4"},{"MeasureID":1008,"GeoType":"Borough","GeoID":3,"Time":"2007","ban_summary_flag":0,"Value":0.9,"CI":"","Note":"","DisplayValue":"0.9"},{"MeasureID":1008,"GeoType":"Borough","GeoID":3,"Time":"2006","ban_summary_flag":0,"Value":1.3,"CI":"","Note":"","DisplayValue":"1.3"},{"MeasureID":1008,"GeoType":"Borough","GeoID":3,"Time":"2005","ban_summary_flag":0,"Value":1.2,"CI":"","Note":"","DisplayValue":"1.2"},{"MeasureID":1008,"GeoType":"Borough","GeoID":3,"Time":"2004","ban_summary_flag":0,"Value":0.8,"CI":"","Note":"","DisplayValue":"0.8"},{"MeasureID":1008,"GeoType":"Borough","GeoID":3,"Time":"2003","ban_summary_flag":0,"Value":1.2,"CI":"","Note":"","DisplayValue":"1.2"},{"MeasureID":1008,"GeoType":"Borough","GeoID":3,"Time":"2002","ban_summary_flag":0,"Value":0.8,"CI":"","Note":"","DisplayValue":"0.8"},{"MeasureID":1008,"GeoType":"Borough","GeoID":3,"Time":"2001","ban_summary_flag":0,"Value":0.6,"CI":"","Note":"","DisplayValue":"0.6"},{"MeasureID":1008,"GeoType":"Borough","GeoID":3,"Time":"2000","ban_summary_flag":0,"Value":0.5,"CI":"","Note":"","DisplayValue":"0.5"},{"MeasureID":1008,"GeoType":"Borough","GeoID":4,"Time":"2020","ban_summary_flag":0,"Value":0.5,"CI":"","Note":"","DisplayValue":"0.5"},{"MeasureID":1008,"GeoType":"Borough","GeoID":4,"Time":"2019","ban_summary_flag":0,"Value":0.6,"CI":"","Note":"","DisplayValue":"0.6"},{"MeasureID":1008,"GeoType":"Borough","GeoID":4,"Time":"2018","ban_summary_flag":0,"Value":0.5,"CI":"","Note":"","DisplayValue":"0.5"},{"MeasureID":1008,"GeoType":"Borough","GeoID":4,"Time":"2017","ban_summary_flag":0,"Value":0.4,"CI":"","Note":"","DisplayValue":"0.4"},{"MeasureID":1008,"GeoType":"Borough","GeoID":4,"Time":"2016","ban_summary_flag":0,"Value":0.5,"CI":"","Note":"","DisplayValue":"0.5"},{"MeasureID":1008,"GeoType":"Borough","GeoID":4,"Time":"2015","ban_summary_flag":0,"Value":0.7,"CI":"","Note":"","DisplayValue":"0.7"},{"MeasureID":1008,"GeoType":"Borough","GeoID":4,"Time":"2014","ban_summary_flag":0,"Value":0.5,"CI":"","Note":"","DisplayValue":"0.5"},{"MeasureID":1008,"GeoType":"Borough","GeoID":4,"Time":"2013","ban_summary_flag":0,"Value":0.5,"CI":"","Note":"","DisplayValue":"0.5"},{"MeasureID":1008,"GeoType":"Borough","GeoID":4,"Time":"2012","ban_summary_flag":0,"Value":0.3,"CI":"","Note":"","DisplayValue":"0.3"},{"MeasureID":1008,"GeoType":"Borough","GeoID":4,"Time":"2011","ban_summary_flag":0,"Value":0.6,"CI":"","Note":"","DisplayValue":"0.6"},{"MeasureID":1008,"GeoType":"Borough","GeoID":4,"Time":"2010","ban_summary_flag":0,"Value":0.4,"CI":"","Note":"","DisplayValue":"0.4"},{"MeasureID":1008,"GeoType":"Borough","GeoID":4,"Time":"2009","ban_summary_flag":0,"Value":0.3,"CI":"","Note":"","DisplayValue":"0.3"},{"MeasureID":1008,"GeoType":"Borough","GeoID":4,"Time":"2008","ban_summary_flag":0,"Value":0.4,"CI":"","Note":"","DisplayValue":"0.4"},{"MeasureID":1008,"GeoType":"Borough","GeoID":4,"Time":"2007","ban_summary_flag":0,"Value":0.1,"CI":"","Note":"","DisplayValue":"0.1"},{"MeasureID":1008,"GeoType":"Borough","GeoID":4,"Time":"2006","ban_summary_flag":0,"Value":0.4,"CI":"","Note":"","DisplayValue":"0.4"},{"MeasureID":1008,"GeoType":"Borough","GeoID":4,"Time":"2005","ban_summary_flag":0,"Value":0,"CI":"","Note":"","DisplayValue":"0.0"},{"MeasureID":1008,"GeoType":"Borough","GeoID":4,"Time":"2004","ban_summary_flag":0,"Value":0.1,"CI":"","Note":"","DisplayValue":"0.1"},{"MeasureID":1008,"GeoType":"Borough","GeoID":4,"Time":"2003","ban_summary_flag":0,"Value":0.2,"CI":"","Note":"","DisplayValue":"0.2"},{"MeasureID":1008,"GeoType":"Borough","GeoID":4,"Time":"2002","ban_summary_flag":0,"Value":0,"CI":"","Note":"","DisplayValue":"0.0"},{"MeasureID":1008,"GeoType":"Borough","GeoID":4,"Time":"2001","ban_summary_flag":0,"Value":0.4,"CI":"","Note":"","DisplayValue":"0.4"},{"MeasureID":1008,"GeoType":"Borough","GeoID":4,"Time":"2000","ban_summary_flag":0,"Value":0.1,"CI":"","Note":"","DisplayValue":"0.1"},{"MeasureID":1008,"GeoType":"Borough","GeoID":5,"Time":"2020","ban_summary_flag":0,"Value":2.3,"CI":"","Note":"","DisplayValue":"2.3"},{"MeasureID":1008,"GeoType":"Borough","GeoID":5,"Time":"2019","ban_summary_flag":0,"Value":1.7,"CI":"","Note":"","DisplayValue":"1.7"},{"MeasureID":1008,"GeoType":"Borough","GeoID":5,"Time":"2018","ban_summary_flag":0,"Value":2.7,"CI":"","Note":"","DisplayValue":"2.7"},{"MeasureID":1008,"GeoType":"Borough","GeoID":5,"Time":"2017","ban_summary_flag":0,"Value":1.7,"CI":"","Note":"","DisplayValue":"1.7"},{"MeasureID":1008,"GeoType":"Borough","GeoID":5,"Time":"2016","ban_summary_flag":0,"Value":0.6,"CI":"","Note":"","DisplayValue":"0.6"},{"MeasureID":1008,"GeoType":"Borough","GeoID":5,"Time":"2015","ban_summary_flag":0,"Value":0.4,"CI":"","Note":"","DisplayValue":"0.4"},{"MeasureID":1008,"GeoType":"Borough","GeoID":5,"Time":"2014","ban_summary_flag":0,"Value":0.2,"CI":"","Note":"","DisplayValue":"0.2"},{"MeasureID":1008,"GeoType":"Borough","GeoID":5,"Time":"2013","ban_summary_flag":0,"Value":0.2,"CI":"","Note":"","DisplayValue":"0.2"},{"MeasureID":1008,"GeoType":"Borough","GeoID":5,"Time":"2012","ban_summary_flag":0,"Value":0,"CI":"","Note":"","DisplayValue":"0.0"},{"MeasureID":1008,"GeoType":"Borough","GeoID":5,"Time":"2011","ban_summary_flag":0,"Value":0.2,"CI":"","Note":"","DisplayValue":"0.2"},{"MeasureID":1008,"GeoType":"Borough","GeoID":5,"Time":"2010","ban_summary_flag":0,"Value":0,"CI":"","Note":"","DisplayValue":"0.0"},{"MeasureID":1008,"GeoType":"Borough","GeoID":5,"Time":"2009","ban_summary_flag":0,"Value":0,"CI":"","Note":"","DisplayValue":"0.0"},{"MeasureID":1008,"GeoType":"Borough","GeoID":5,"Time":"2008","ban_summary_flag":0,"Value":0.2,"CI":"","Note":"","DisplayValue":"0.2"},{"MeasureID":1008,"GeoType":"Borough","GeoID":5,"Time":"2007","ban_summary_flag":0,"Value":0,"CI":"","Note":"","DisplayValue":"0.0"},{"MeasureID":1008,"GeoType":"Borough","GeoID":5,"Time":"2006","ban_summary_flag":0,"Value":0.4,"CI":"","Note":"","DisplayValue":"0.4"},{"MeasureID":1008,"GeoType":"Borough","GeoID":5,"Time":"2005","ban_summary_flag":0,"Value":0,"CI":"","Note":"","DisplayValue":"0.0"},{"MeasureID":1008,"GeoType":"Borough","GeoID":5,"Time":"2004","ban_summary_flag":0,"Value":0,"CI":"","Note":"","DisplayValue":"0.0"},{"MeasureID":1008,"GeoType":"Borough","GeoID":5,"Time":"2003","ban_summary_flag":0,"Value":0.2,"CI":"","Note":"","DisplayValue":"0.2"},{"MeasureID":1008,"GeoType":"Borough","GeoID":5,"Time":"2002","ban_summary_flag":0,"Value":0,"CI":"","Note":"","DisplayValue":"0.0"},{"MeasureID":1008,"GeoType":"Borough","GeoID":5,"Time":"2001","ban_summary_flag":0,"Value":0,"CI":"","Note":"","DisplayValue":"0.0"},{"MeasureID":1008,"GeoType":"Borough","GeoID":5,"Time":"2000","ban_summary_flag":0,"Value":0,"CI":"","Note":"","DisplayValue":"0.0"},{"MeasureID":1008,"GeoType":"Citywide","GeoID":1,"Time":"2020","ban_summary_flag":0,"Value":1,"CI":"","Note":"","DisplayValue":"1.0"},{"MeasureID":1008,"GeoType":"Citywide","GeoID":1,"Time":"2019","ban_summary_flag":0,"Value":1,"CI":"","Note":"","DisplayValue":"1.0"},{"MeasureID":1008,"GeoType":"Citywide","GeoID":1,"Time":"2018","ban_summary_flag":0,"Value":1,"CI":"","Note":"","DisplayValue":"1.0"},{"MeasureID":1008,"GeoType":"Citywide","GeoID":1,"Time":"2017","ban_summary_flag":0,"Value":1.1,"CI":"","Note":"","DisplayValue":"1.1"},{"MeasureID":1008,"GeoType":"Citywide","GeoID":1,"Time":"2016","ban_summary_flag":0,"Value":0.6,"CI":"","Note":"","DisplayValue":"0.6"},{"MeasureID":1008,"GeoType":"Citywide","GeoID":1,"Time":"2015","ban_summary_flag":0,"Value":0.8,"CI":"","Note":"","DisplayValue":"0.8"},{"MeasureID":1008,"GeoType":"Citywide","GeoID":1,"Time":"2014","ban_summary_flag":0,"Value":0.6,"CI":"","Note":"","DisplayValue":"0.6"},{"MeasureID":1008,"GeoType":"Citywide","GeoID":1,"Time":"2013","ban_summary_flag":0,"Value":0.9,"CI":"","Note":"","DisplayValue":"0.9"},{"MeasureID":1008,"GeoType":"Citywide","GeoID":1,"Time":"2012","ban_summary_flag":0,"Value":0.3,"CI":"","Note":"","DisplayValue":"0.3"},{"MeasureID":1008,"GeoType":"Citywide","GeoID":1,"Time":"2011","ban_summary_flag":0,"Value":0.7,"CI":"","Note":"","DisplayValue":"0.7"},{"MeasureID":1008,"GeoType":"Citywide","GeoID":1,"Time":"2010","ban_summary_flag":0,"Value":0.4,"CI":"","Note":"","DisplayValue":"0.4"},{"MeasureID":1008,"GeoType":"Citywide","GeoID":1,"Time":"2009","ban_summary_flag":0,"Value":0.5,"CI":"","Note":"","DisplayValue":"0.5"},{"MeasureID":1008,"GeoType":"Citywide","GeoID":1,"Time":"2008","ban_summary_flag":0,"Value":0.5,"CI":"","Note":"","DisplayValue":"0.5"},{"MeasureID":1008,"GeoType":"Citywide","GeoID":1,"Time":"2007","ban_summary_flag":0,"Value":0.3,"CI":"","Note":"","DisplayValue":"0.3"},{"MeasureID":1008,"GeoType":"Citywide","GeoID":1,"Time":"2006","ban_summary_flag":0,"Value":0.5,"CI":"","Note":"","DisplayValue":"0.5"},{"MeasureID":1008,"GeoType":"Citywide","GeoID":1,"Time":"2005","ban_summary_flag":0,"Value":0.3,"CI":"","Note":"","DisplayValue":"0.3"},{"MeasureID":1008,"GeoType":"Citywide","GeoID":1,"Time":"2004","ban_summary_flag":0,"Value":0.2,"CI":"","Note":"","DisplayValue":"0.2"},{"MeasureID":1008,"GeoType":"Citywide","GeoID":1,"Time":"2003","ban_summary_flag":0,"Value":0.3,"CI":"","Note":"","DisplayValue":"0.3"},{"MeasureID":1008,"GeoType":"Citywide","GeoID":1,"Time":"2002","ban_summary_flag":0,"Value":0.2,"CI":"","Note":"","DisplayValue":"0.2"},{"MeasureID":1008,"GeoType":"Citywide","GeoID":1,"Time":"2001","ban_summary_flag":0,"Value":0.2,"CI":"","Note":"","DisplayValue":"0.2"},{"MeasureID":1008,"GeoType":"Citywide","GeoID":1,"Time":"2000","ban_summary_flag":0,"Value":0.1,"CI":"","Note":"","DisplayValue":"0.1"}]
