[{"MeasureID":1244,"MeasureName":"Carbon Monoxide Deaths, Fire-Related Number","MeasurementType":"Fire-Related Number","GeoType":"Citywide","GeoID":1,"Time":"2017","Value":0,"DisplayValue":"0","CI":"","Note":""},{"MeasureID":1244,"MeasureName":"Carbon Monoxide Deaths, Fire-Related Number","MeasurementType":"Fire-Related Number","GeoType":"Citywide","GeoID":1,"Time":"2016","Value":0,"DisplayValue":"0","CI":"","Note":""},{"MeasureID":1244,"MeasureName":"Carbon Monoxide Deaths, Fire-Related Number","MeasurementType":"Fire-Related Number","GeoType":"Citywide","GeoID":1,"Time":"2015","Value":0,"DisplayValue":"0","CI":"","Note":""},{"MeasureID":1244,"MeasureName":"Carbon Monoxide Deaths, Fire-Related Number","MeasurementType":"Fire-Related Number","GeoType":"Citywide","GeoID":1,"Time":"2014","Value":1,"DisplayValue":"1","CI":"","Note":""},{"MeasureID":1244,"MeasureName":"Carbon Monoxide Deaths, Fire-Related Number","MeasurementType":"Fire-Related Number","GeoType":"Citywide","GeoID":1,"Time":"2013","Value":3,"DisplayValue":"3","CI":"","Note":""},{"MeasureID":1244,"MeasureName":"Carbon Monoxide Deaths, Fire-Related Number","MeasurementType":"Fire-Related Number","GeoType":"Citywide","GeoID":1,"Time":"2012","Value":0,"DisplayValue":"0","CI":"","Note":""},{"MeasureID":1244,"MeasureName":"Carbon Monoxide Deaths, Fire-Related Number","MeasurementType":"Fire-Related Number","GeoType":"Citywide","GeoID":1,"Time":"2011","Value":1,"DisplayValue":"1","CI":"","Note":""},{"MeasureID":1244,"MeasureName":"Carbon Monoxide Deaths, Fire-Related Number","MeasurementType":"Fire-Related Number","GeoType":"Citywide","GeoID":1,"Time":"2010","Value":1,"DisplayValue":"1","CI":"","Note":""},{"MeasureID":1244,"MeasureName":"Carbon Monoxide Deaths, Fire-Related Number","MeasurementType":"Fire-Related Number","GeoType":"Citywide","GeoID":1,"Time":"2009","Value":1,"DisplayValue":"1","CI":"","Note":""},{"MeasureID":1244,"MeasureName":"Carbon Monoxide Deaths, Fire-Related Number","MeasurementType":"Fire-Related Number","GeoType":"Citywide","GeoID":1,"Time":"2008","Value":0,"DisplayValue":"0","CI":"","Note":""},{"MeasureID":1244,"MeasureName":"Carbon Monoxide Deaths, Fire-Related Number","MeasurementType":"Fire-Related Number","GeoType":"Citywide","GeoID":1,"Time":"2007","Value":3,"DisplayValue":"3","CI":"","Note":""},{"MeasureID":1244,"MeasureName":"Carbon Monoxide Deaths, Fire-Related Number","MeasurementType":"Fire-Related Number","GeoType":"Citywide","GeoID":1,"Time":"2006","Value":1,"DisplayValue":"1","CI":"","Note":""},{"MeasureID":1244,"MeasureName":"Carbon Monoxide Deaths, Fire-Related Number","MeasurementType":"Fire-Related Number","GeoType":"Citywide","GeoID":1,"Time":"2005","Value":0,"DisplayValue":"0","CI":"","Note":""},{"MeasureID":1244,"MeasureName":"Carbon Monoxide Deaths, Fire-Related Number","MeasurementType":"Fire-Related Number","GeoType":"Citywide","GeoID":1,"Time":"2004","Value":1,"DisplayValue":"1","CI":"","Note":""},{"MeasureID":1244,"MeasureName":"Carbon Monoxide Deaths, Fire-Related Number","MeasurementType":"Fire-Related Number","GeoType":"Citywide","GeoID":1,"Time":"2003","Value":0,"DisplayValue":"0","CI":"","Note":""},{"MeasureID":1244,"MeasureName":"Carbon Monoxide Deaths, Fire-Related Number","MeasurementType":"Fire-Related Number","GeoType":"Citywide","GeoID":1,"Time":"2002","Value":4,"DisplayValue":"4","CI":"","Note":""},{"MeasureID":1244,"MeasureName":"Carbon Monoxide Deaths, Fire-Related Number","MeasurementType":"Fire-Related Number","GeoType":"Citywide","GeoID":1,"Time":"2001","Value":2,"DisplayValue":"2","CI":"","Note":""},{"MeasureID":1244,"MeasureName":"Carbon Monoxide Deaths, Fire-Related Number","MeasurementType":"Fire-Related Number","GeoType":"Citywide","GeoID":1,"Time":"2000","Value":2,"DisplayValue":"2","CI":"","Note":""},{"MeasureID":1245,"MeasureName":"Carbon Monoxide Deaths, Non-Fire-Related Number","MeasurementType":"Non-Fire-Related Number","GeoType":"Citywide","GeoID":1,"Time":"2017","Value":2,"DisplayValue":"2","CI":"","Note":""},{"MeasureID":1245,"MeasureName":"Carbon Monoxide Deaths, Non-Fire-Related Number","MeasurementType":"Non-Fire-Related Number","GeoType":"Citywide","GeoID":1,"Time":"2016","Value":6,"DisplayValue":"6","CI":"","Note":""},{"MeasureID":1245,"MeasureName":"Carbon Monoxide Deaths, Non-Fire-Related Number","MeasurementType":"Non-Fire-Related Number","GeoType":"Citywide","GeoID":1,"Time":"2015","Value":7,"DisplayValue":"7","CI":"","Note":""},{"MeasureID":1245,"MeasureName":"Carbon Monoxide Deaths, Non-Fire-Related Number","MeasurementType":"Non-Fire-Related Number","GeoType":"Citywide","GeoID":1,"Time":"2014","Value":0,"DisplayValue":"0","CI":"","Note":""},{"MeasureID":1245,"MeasureName":"Carbon Monoxide Deaths, Non-Fire-Related Number","MeasurementType":"Non-Fire-Related Number","GeoType":"Citywide","GeoID":1,"Time":"2013","Value":3,"DisplayValue":"3","CI":"","Note":""},{"MeasureID":1245,"MeasureName":"Carbon Monoxide Deaths, Non-Fire-Related Number","MeasurementType":"Non-Fire-Related Number","GeoType":"Citywide","GeoID":1,"Time":"2012","Value":5,"DisplayValue":"5","CI":"","Note":""},{"MeasureID":1245,"MeasureName":"Carbon Monoxide Deaths, Non-Fire-Related Number","MeasurementType":"Non-Fire-Related Number","GeoType":"Citywide","GeoID":1,"Time":"2011","Value":2,"DisplayValue":"2","CI":"","Note":""},{"MeasureID":1245,"MeasureName":"Carbon Monoxide Deaths, Non-Fire-Related Number","MeasurementType":"Non-Fire-Related Number","GeoType":"Citywide","GeoID":1,"Time":"2010","Value":2,"DisplayValue":"2","CI":"","Note":""},{"MeasureID":1245,"MeasureName":"Carbon Monoxide Deaths, Non-Fire-Related Number","MeasurementType":"Non-Fire-Related Number","GeoType":"Citywide","GeoID":1,"Time":"2009","Value":2,"DisplayValue":"2","CI":"","Note":""},{"MeasureID":1245,"MeasureName":"Carbon Monoxide Deaths, Non-Fire-Related Number","MeasurementType":"Non-Fire-Related Number","GeoType":"Citywide","GeoID":1,"Time":"2008","Value":0,"DisplayValue":"0","CI":"","Note":""},{"MeasureID":1245,"MeasureName":"Carbon Monoxide Deaths, Non-Fire-Related Number","MeasurementType":"Non-Fire-Related Number","GeoType":"Citywide","GeoID":1,"Time":"2007","Value":3,"DisplayValue":"3","CI":"","Note":""},{"MeasureID":1245,"MeasureName":"Carbon Monoxide Deaths, Non-Fire-Related Number","MeasurementType":"Non-Fire-Related Number","GeoType":"Citywide","GeoID":1,"Time":"2006","Value":5,"DisplayValue":"5","CI":"","Note":""},{"MeasureID":1245,"MeasureName":"Carbon Monoxide Deaths, Non-Fire-Related Number","MeasurementType":"Non-Fire-Related Number","GeoType":"Citywide","GeoID":1,"Time":"2005","Value":11,"DisplayValue":"11","CI":"","Note":""},{"MeasureID":1245,"MeasureName":"Carbon Monoxide Deaths, Non-Fire-Related Number","MeasurementType":"Non-Fire-Related Number","GeoType":"Citywide","GeoID":1,"Time":"2004","Value":6,"DisplayValue":"6","CI":"","Note":""},{"MeasureID":1245,"MeasureName":"Carbon Monoxide Deaths, Non-Fire-Related Number","MeasurementType":"Non-Fire-Related Number","GeoType":"Citywide","GeoID":1,"Time":"2003","Value":12,"DisplayValue":"12","CI":"","Note":""},{"MeasureID":1245,"MeasureName":"Carbon Monoxide Deaths, Non-Fire-Related Number","MeasurementType":"Non-Fire-Related Number","GeoType":"Citywide","GeoID":1,"Time":"2002","Value":10,"DisplayValue":"10","CI":"","Note":""},{"MeasureID":1245,"MeasureName":"Carbon Monoxide Deaths, Non-Fire-Related Number","MeasurementType":"Non-Fire-Related Number","GeoType":"Citywide","GeoID":1,"Time":"2001","Value":3,"DisplayValue":"3","CI":"","Note":""},{"MeasureID":1245,"MeasureName":"Carbon Monoxide Deaths, Non-Fire-Related Number","MeasurementType":"Non-Fire-Related Number","GeoType":"Citywide","GeoID":1,"Time":"2000","Value":1,"DisplayValue":"1","CI":"","Note":""},{"MeasureID":1246,"MeasureName":"Carbon Monoxide Deaths, Unknown cause number","MeasurementType":"Unknown cause number","GeoType":"Citywide","GeoID":1,"Time":"2017","Value":1,"DisplayValue":"1","CI":"","Note":""},{"MeasureID":1246,"MeasureName":"Carbon Monoxide Deaths, Unknown cause number","MeasurementType":"Unknown cause number","GeoType":"Citywide","GeoID":1,"Time":"2016","Value":1,"DisplayValue":"1","CI":"","Note":""},{"MeasureID":1246,"MeasureName":"Carbon Monoxide Deaths, Unknown cause number","MeasurementType":"Unknown cause number","GeoType":"Citywide","GeoID":1,"Time":"2015","Value":0,"DisplayValue":"0","CI":"","Note":""},{"MeasureID":1246,"MeasureName":"Carbon Monoxide Deaths, Unknown cause number","MeasurementType":"Unknown cause number","GeoType":"Citywide","GeoID":1,"Time":"2014","Value":2,"DisplayValue":"2","CI":"","Note":""},{"MeasureID":1246,"MeasureName":"Carbon Monoxide Deaths, Unknown cause number","MeasurementType":"Unknown cause number","GeoType":"Citywide","GeoID":1,"Time":"2013","Value":2,"DisplayValue":"2","CI":"","Note":""},{"MeasureID":1246,"MeasureName":"Carbon Monoxide Deaths, Unknown cause number","MeasurementType":"Unknown cause number","GeoType":"Citywide","GeoID":1,"Time":"2012","Value":0,"DisplayValue":"0","CI":"","Note":""},{"MeasureID":1246,"MeasureName":"Carbon Monoxide Deaths, Unknown cause number","MeasurementType":"Unknown cause number","GeoType":"Citywide","GeoID":1,"Time":"2011","Value":1,"DisplayValue":"1","CI":"","Note":""},{"MeasureID":1246,"MeasureName":"Carbon Monoxide Deaths, Unknown cause number","MeasurementType":"Unknown cause number","GeoType":"Citywide","GeoID":1,"Time":"2010","Value":0,"DisplayValue":"0","CI":"","Note":""},{"MeasureID":1246,"MeasureName":"Carbon Monoxide Deaths, Unknown cause number","MeasurementType":"Unknown cause number","GeoType":"Citywide","GeoID":1,"Time":"2009","Value":0,"DisplayValue":"0","CI":"","Note":""},{"MeasureID":1246,"MeasureName":"Carbon Monoxide Deaths, Unknown cause number","MeasurementType":"Unknown cause number","GeoType":"Citywide","GeoID":1,"Time":"2008","Value":0,"DisplayValue":"0","CI":"","Note":""},{"MeasureID":1246,"MeasureName":"Carbon Monoxide Deaths, Unknown cause number","MeasurementType":"Unknown cause number","GeoType":"Citywide","GeoID":1,"Time":"2007","Value":0,"DisplayValue":"0","CI":"","Note":""},{"MeasureID":1246,"MeasureName":"Carbon Monoxide Deaths, Unknown cause number","MeasurementType":"Unknown cause number","GeoType":"Citywide","GeoID":1,"Time":"2006","Value":0,"DisplayValue":"0","CI":"","Note":""},{"MeasureID":1246,"MeasureName":"Carbon Monoxide Deaths, Unknown cause number","MeasurementType":"Unknown cause number","GeoType":"Citywide","GeoID":1,"Time":"2005","Value":3,"DisplayValue":"3","CI":"","Note":""},{"MeasureID":1246,"MeasureName":"Carbon Monoxide Deaths, Unknown cause number","MeasurementType":"Unknown cause number","GeoType":"Citywide","GeoID":1,"Time":"2004","Value":1,"DisplayValue":"1","CI":"","Note":""},{"MeasureID":1246,"MeasureName":"Carbon Monoxide Deaths, Unknown cause number","MeasurementType":"Unknown cause number","GeoType":"Citywide","GeoID":1,"Time":"2003","Value":2,"DisplayValue":"2","CI":"","Note":""},{"MeasureID":1246,"MeasureName":"Carbon Monoxide Deaths, Unknown cause number","MeasurementType":"Unknown cause number","GeoType":"Citywide","GeoID":1,"Time":"2002","Value":2,"DisplayValue":"2","CI":"","Note":""},{"MeasureID":1246,"MeasureName":"Carbon Monoxide Deaths, Unknown cause number","MeasurementType":"Unknown cause number","GeoType":"Citywide","GeoID":1,"Time":"2001","Value":0,"DisplayValue":"0","CI":"","Note":""},{"MeasureID":1246,"MeasureName":"Carbon Monoxide Deaths, Unknown cause number","MeasurementType":"Unknown cause number","GeoType":"Citywide","GeoID":1,"Time":"2000","Value":0,"DisplayValue":"0","CI":"","Note":""}]
