[{"MeasureID":814,"GeoID":1,"GeoType":"Borough","TimePeriodID":15,"ban_summary_flag":0,"Value":31,"CI":"","Note":"","DisplayValue":"31"},{"MeasureID":814,"GeoID":1,"GeoType":"Borough","TimePeriodID":26,"ban_summary_flag":0,"Value":24,"CI":"","Note":"","DisplayValue":"24"},{"MeasureID":814,"GeoID":1,"GeoType":"Borough","TimePeriodID":28,"ban_summary_flag":0,"Value":32,"CI":"","Note":"","DisplayValue":"32"},{"MeasureID":814,"GeoID":1,"GeoType":"Borough","TimePeriodID":29,"ban_summary_flag":0,"Value":27,"CI":"","Note":"","DisplayValue":"27"},{"MeasureID":814,"GeoID":1,"GeoType":"Borough","TimePeriodID":30,"ban_summary_flag":0,"Value":27,"CI":"","Note":"","DisplayValue":"27"},{"MeasureID":814,"GeoID":1,"GeoType":"Borough","TimePeriodID":31,"ban_summary_flag":0,"Value":30,"CI":"","Note":"","DisplayValue":"30"},{"MeasureID":814,"GeoID":1,"GeoType":"Borough","TimePeriodID":32,"ban_summary_flag":0,"Value":32,"CI":"","Note":"","DisplayValue":"32"},{"MeasureID":814,"GeoID":1,"GeoType":"Borough","TimePeriodID":177,"ban_summary_flag":0,"Value":28,"CI":"","Note":"","DisplayValue":"28"},{"MeasureID":814,"GeoID":1,"GeoType":"Borough","TimePeriodID":220,"ban_summary_flag":0,"Value":28,"CI":"","Note":"","DisplayValue":"28"},{"MeasureID":814,"GeoID":1,"GeoType":"Borough","TimePeriodID":221,"ban_summary_flag":0,"Value":31,"CI":"","Note":"","DisplayValue":"31"},{"MeasureID":814,"GeoID":1,"GeoType":"Borough","TimePeriodID":222,"ban_summary_flag":0,"Value":32,"CI":"","Note":"","DisplayValue":"32"},{"MeasureID":814,"GeoID":2,"GeoType":"Borough","TimePeriodID":15,"ban_summary_flag":0,"Value":42,"CI":"","Note":"","DisplayValue":"42"},{"MeasureID":814,"GeoID":2,"GeoType":"Borough","TimePeriodID":26,"ban_summary_flag":0,"Value":49,"CI":"","Note":"","DisplayValue":"49"},{"MeasureID":814,"GeoID":2,"GeoType":"Borough","TimePeriodID":28,"ban_summary_flag":0,"Value":43,"CI":"","Note":"","DisplayValue":"43"},{"MeasureID":814,"GeoID":2,"GeoType":"Borough","TimePeriodID":29,"ban_summary_flag":0,"Value":47,"CI":"","Note":"","DisplayValue":"47"},{"MeasureID":814,"GeoID":2,"GeoType":"Borough","TimePeriodID":30,"ban_summary_flag":0,"Value":61,"CI":"","Note":"","DisplayValue":"61"},{"MeasureID":814,"GeoID":2,"GeoType":"Borough","TimePeriodID":31,"ban_summary_flag":0,"Value":59,"CI":"","Note":"","DisplayValue":"59"},{"MeasureID":814,"GeoID":2,"GeoType":"Borough","TimePeriodID":32,"ban_summary_flag":0,"Value":59,"CI":"","Note":"","DisplayValue":"59"},{"MeasureID":814,"GeoID":2,"GeoType":"Borough","TimePeriodID":177,"ban_summary_flag":0,"Value":51,"CI":"","Note":"","DisplayValue":"51"},{"MeasureID":814,"GeoID":2,"GeoType":"Borough","TimePeriodID":220,"ban_summary_flag":0,"Value":50,"CI":"","Note":"","DisplayValue":"50"},{"MeasureID":814,"GeoID":2,"GeoType":"Borough","TimePeriodID":221,"ban_summary_flag":0,"Value":56,"CI":"","Note":"","DisplayValue":"56"},{"MeasureID":814,"GeoID":2,"GeoType":"Borough","TimePeriodID":222,"ban_summary_flag":0,"Value":50,"CI":"","Note":"","DisplayValue":"50"},{"MeasureID":814,"GeoID":3,"GeoType":"Borough","TimePeriodID":15,"ban_summary_flag":0,"Value":22,"CI":"","Note":"","DisplayValue":"22"},{"MeasureID":814,"GeoID":3,"GeoType":"Borough","TimePeriodID":26,"ban_summary_flag":0,"Value":19,"CI":"","Note":"","DisplayValue":"19"},{"MeasureID":814,"GeoID":3,"GeoType":"Borough","TimePeriodID":28,"ban_summary_flag":0,"Value":25,"CI":"","Note":"","DisplayValue":"25"},{"MeasureID":814,"GeoID":3,"GeoType":"Borough","TimePeriodID":29,"ban_summary_flag":0,"Value":24,"CI":"","Note":"","DisplayValue":"24"},{"MeasureID":814,"GeoID":3,"GeoType":"Borough","TimePeriodID":30,"ban_summary_flag":0,"Value":20,"CI":"","Note":"","DisplayValue":"20"},{"MeasureID":814,"GeoID":3,"GeoType":"Borough","TimePeriodID":31,"ban_summary_flag":0,"Value":22,"CI":"","Note":"","DisplayValue":"22"},{"MeasureID":814,"GeoID":3,"GeoType":"Borough","TimePeriodID":32,"ban_summary_flag":0,"Value":25,"CI":"","Note":"","DisplayValue":"25"},{"MeasureID":814,"GeoID":3,"GeoType":"Borough","TimePeriodID":177,"ban_summary_flag":0,"Value":12,"CI":"","Note":"","DisplayValue":"12"},{"MeasureID":814,"GeoID":3,"GeoType":"Borough","TimePeriodID":220,"ban_summary_flag":0,"Value":28,"CI":"","Note":"","DisplayValue":"28"},{"MeasureID":814,"GeoID":3,"GeoType":"Borough","TimePeriodID":221,"ban_summary_flag":0,"Value":21,"CI":"","Note":"","DisplayValue":"21"},{"MeasureID":814,"GeoID":3,"GeoType":"Borough","TimePeriodID":222,"ban_summary_flag":0,"Value":8,"CI":"","Note":"","DisplayValue":"8"},{"MeasureID":814,"GeoID":4,"GeoType":"Borough","TimePeriodID":15,"ban_summary_flag":0,"Value":40,"CI":"","Note":"","DisplayValue":"40"},{"MeasureID":814,"GeoID":4,"GeoType":"Borough","TimePeriodID":26,"ban_summary_flag":0,"Value":42,"CI":"","Note":"","DisplayValue":"42"},{"MeasureID":814,"GeoID":4,"GeoType":"Borough","TimePeriodID":28,"ban_summary_flag":0,"Value":36,"CI":"","Note":"","DisplayValue":"36"},{"MeasureID":814,"GeoID":4,"GeoType":"Borough","TimePeriodID":29,"ban_summary_flag":0,"Value":29,"CI":"","Note":"","DisplayValue":"29"},{"MeasureID":814,"GeoID":4,"GeoType":"Borough","TimePeriodID":30,"ban_summary_flag":0,"Value":30,"CI":"","Note":"","DisplayValue":"30"},{"MeasureID":814,"GeoID":4,"GeoType":"Borough","TimePeriodID":31,"ban_summary_flag":0,"Value":32,"CI":"","Note":"","DisplayValue":"32"},{"MeasureID":814,"GeoID":4,"GeoType":"Borough","TimePeriodID":32,"ban_summary_flag":0,"Value":34,"CI":"","Note":"","DisplayValue":"34"},{"MeasureID":814,"GeoID":4,"GeoType":"Borough","TimePeriodID":177,"ban_summary_flag":0,"Value":39,"CI":"","Note":"","DisplayValue":"39"},{"MeasureID":814,"GeoID":4,"GeoType":"Borough","TimePeriodID":220,"ban_summary_flag":0,"Value":37,"CI":"","Note":"","DisplayValue":"37"},{"MeasureID":814,"GeoID":4,"GeoType":"Borough","TimePeriodID":221,"ban_summary_flag":0,"Value":41,"CI":"","Note":"","DisplayValue":"41"},{"MeasureID":814,"GeoID":4,"GeoType":"Borough","TimePeriodID":222,"ban_summary_flag":0,"Value":37,"CI":"","Note":"","DisplayValue":"37"},{"MeasureID":814,"GeoID":5,"GeoType":"Borough","TimePeriodID":15,"ban_summary_flag":0,"Value":5,"CI":"","Note":"","DisplayValue":"5"},{"MeasureID":814,"GeoID":5,"GeoType":"Borough","TimePeriodID":26,"ban_summary_flag":0,"Value":4,"CI":"","Note":"","DisplayValue":"4"},{"MeasureID":814,"GeoID":5,"GeoType":"Borough","TimePeriodID":28,"ban_summary_flag":0,"Value":6,"CI":"","Note":"","DisplayValue":"6"},{"MeasureID":814,"GeoID":5,"GeoType":"Borough","TimePeriodID":29,"ban_summary_flag":0,"Value":8,"CI":"","Note":"","DisplayValue":"8"},{"MeasureID":814,"GeoID":5,"GeoType":"Borough","TimePeriodID":30,"ban_summary_flag":0,"Value":5,"CI":"","Note":"","DisplayValue":"5"},{"MeasureID":814,"GeoID":5,"GeoType":"Borough","TimePeriodID":31,"ban_summary_flag":0,"Value":5,"CI":"","Note":"","DisplayValue":"5"},{"MeasureID":814,"GeoID":5,"GeoType":"Borough","TimePeriodID":32,"ban_summary_flag":0,"Value":2,"CI":"","Note":"","DisplayValue":"2"},{"MeasureID":814,"GeoID":5,"GeoType":"Borough","TimePeriodID":177,"ban_summary_flag":0,"Value":6,"CI":"","Note":"","DisplayValue":"6"},{"MeasureID":814,"GeoID":5,"GeoType":"Borough","TimePeriodID":220,"ban_summary_flag":0,"Value":5,"CI":"","Note":"","DisplayValue":"5"},{"MeasureID":814,"GeoID":5,"GeoType":"Borough","TimePeriodID":221,"ban_summary_flag":0,"Value":5,"CI":"","Note":"","DisplayValue":"5"},{"MeasureID":814,"GeoID":5,"GeoType":"Borough","TimePeriodID":222,"ban_summary_flag":0,"Value":5,"CI":"","Note":"","DisplayValue":"5"},{"MeasureID":814,"GeoID":1,"GeoType":"Citywide","TimePeriodID":15,"ban_summary_flag":0,"Value":140,"CI":"","Note":"","DisplayValue":"140"},{"MeasureID":814,"GeoID":1,"GeoType":"Citywide","TimePeriodID":26,"ban_summary_flag":0,"Value":138,"CI":"","Note":"","DisplayValue":"138"},{"MeasureID":814,"GeoID":1,"GeoType":"Citywide","TimePeriodID":28,"ban_summary_flag":0,"Value":142,"CI":"","Note":"","DisplayValue":"142"},{"MeasureID":814,"GeoID":1,"GeoType":"Citywide","TimePeriodID":29,"ban_summary_flag":0,"Value":135,"CI":"","Note":"","DisplayValue":"135"},{"MeasureID":814,"GeoID":1,"GeoType":"Citywide","TimePeriodID":30,"ban_summary_flag":0,"Value":143,"CI":"","Note":"","DisplayValue":"143"},{"MeasureID":814,"GeoID":1,"GeoType":"Citywide","TimePeriodID":31,"ban_summary_flag":0,"Value":148,"CI":"","Note":"","DisplayValue":"148"},{"MeasureID":814,"GeoID":1,"GeoType":"Citywide","TimePeriodID":32,"ban_summary_flag":0,"Value":152,"CI":"","Note":"","DisplayValue":"152"},{"MeasureID":814,"GeoID":1,"GeoType":"Citywide","TimePeriodID":177,"ban_summary_flag":0,"Value":136,"CI":"","Note":"","DisplayValue":"136"},{"MeasureID":814,"GeoID":1,"GeoType":"Citywide","TimePeriodID":220,"ban_summary_flag":0,"Value":148,"CI":"","Note":"","DisplayValue":"148"},{"MeasureID":814,"GeoID":1,"GeoType":"Citywide","TimePeriodID":221,"ban_summary_flag":0,"Value":154,"CI":"","Note":"","DisplayValue":"154"},{"MeasureID":814,"GeoID":1,"GeoType":"Citywide","TimePeriodID":222,"ban_summary_flag":0,"Value":132,"CI":"","Note":"","DisplayValue":"132"},{"MeasureID":815,"GeoID":1,"GeoType":"Borough","TimePeriodID":15,"ban_summary_flag":0,"Value":4.6,"CI":"","Note":"","DisplayValue":"4.6"},{"MeasureID":815,"GeoID":1,"GeoType":"Borough","TimePeriodID":26,"ban_summary_flag":0,"Value":3.5,"CI":"","Note":"","DisplayValue":"3.5"},{"MeasureID":815,"GeoID":1,"GeoType":"Borough","TimePeriodID":28,"ban_summary_flag":0,"Value":4.8,"CI":"","Note":"","DisplayValue":"4.8"},{"MeasureID":815,"GeoID":1,"GeoType":"Borough","TimePeriodID":29,"ban_summary_flag":0,"Value":4,"CI":"","Note":"","DisplayValue":"4.0"},{"MeasureID":815,"GeoID":1,"GeoType":"Borough","TimePeriodID":30,"ban_summary_flag":0,"Value":4,"CI":"","Note":"","DisplayValue":"4.0"},{"MeasureID":815,"GeoID":1,"GeoType":"Borough","TimePeriodID":31,"ban_summary_flag":0,"Value":4.5,"CI":"","Note":"","DisplayValue":"4.5"},{"MeasureID":815,"GeoID":1,"GeoType":"Borough","TimePeriodID":32,"ban_summary_flag":0,"Value":4.7,"CI":"","Note":"","DisplayValue":"4.7"},{"MeasureID":815,"GeoID":1,"GeoType":"Borough","TimePeriodID":177,"ban_summary_flag":0,"Value":4.2,"CI":"","Note":"","DisplayValue":"4.2"},{"MeasureID":815,"GeoID":1,"GeoType":"Borough","TimePeriodID":220,"ban_summary_flag":0,"Value":4.1,"CI":"","Note":"","DisplayValue":"4.1"},{"MeasureID":815,"GeoID":1,"GeoType":"Borough","TimePeriodID":221,"ban_summary_flag":0,"Value":4.5,"CI":"","Note":"","DisplayValue":"4.5"},{"MeasureID":815,"GeoID":1,"GeoType":"Borough","TimePeriodID":222,"ban_summary_flag":0,"Value":4.9,"CI":"","Note":"","DisplayValue":"4.9"},{"MeasureID":815,"GeoID":2,"GeoType":"Borough","TimePeriodID":15,"ban_summary_flag":0,"Value":3.5,"CI":"","Note":"","DisplayValue":"3.5"},{"MeasureID":815,"GeoID":2,"GeoType":"Borough","TimePeriodID":26,"ban_summary_flag":0,"Value":4.1,"CI":"","Note":"","DisplayValue":"4.1"},{"MeasureID":815,"GeoID":2,"GeoType":"Borough","TimePeriodID":28,"ban_summary_flag":0,"Value":3.6,"CI":"","Note":"","DisplayValue":"3.6"},{"MeasureID":815,"GeoID":2,"GeoType":"Borough","TimePeriodID":29,"ban_summary_flag":0,"Value":4,"CI":"","Note":"","DisplayValue":"4.0"},{"MeasureID":815,"GeoID":2,"GeoType":"Borough","TimePeriodID":30,"ban_summary_flag":0,"Value":5.1,"CI":"","Note":"","DisplayValue":"5.1"},{"MeasureID":815,"GeoID":2,"GeoType":"Borough","TimePeriodID":31,"ban_summary_flag":0,"Value":4.9,"CI":"","Note":"","DisplayValue":"4.9"},{"MeasureID":815,"GeoID":2,"GeoType":"Borough","TimePeriodID":32,"ban_summary_flag":0,"Value":4.8,"CI":"","Note":"","DisplayValue":"4.8"},{"MeasureID":815,"GeoID":2,"GeoType":"Borough","TimePeriodID":177,"ban_summary_flag":0,"Value":4.1,"CI":"","Note":"","DisplayValue":"4.1"},{"MeasureID":815,"GeoID":2,"GeoType":"Borough","TimePeriodID":220,"ban_summary_flag":0,"Value":4,"CI":"","Note":"","DisplayValue":"4.0"},{"MeasureID":815,"GeoID":2,"GeoType":"Borough","TimePeriodID":221,"ban_summary_flag":0,"Value":4.5,"CI":"","Note":"","DisplayValue":"4.5"},{"MeasureID":815,"GeoID":2,"GeoType":"Borough","TimePeriodID":222,"ban_summary_flag":0,"Value":4,"CI":"","Note":"","DisplayValue":"4.0"},{"MeasureID":815,"GeoID":3,"GeoType":"Borough","TimePeriodID":15,"ban_summary_flag":0,"Value":3.6,"CI":"","Note":"","DisplayValue":"3.6"},{"MeasureID":815,"GeoID":3,"GeoType":"Borough","TimePeriodID":26,"ban_summary_flag":0,"Value":3.2,"CI":"","Note":"","DisplayValue":"3.2"},{"MeasureID":815,"GeoID":3,"GeoType":"Borough","TimePeriodID":28,"ban_summary_flag":0,"Value":4.1,"CI":"","Note":"","DisplayValue":"4.1"},{"MeasureID":815,"GeoID":3,"GeoType":"Borough","TimePeriodID":29,"ban_summary_flag":0,"Value":3.9,"CI":"","Note":"","DisplayValue":"3.9"},{"MeasureID":815,"GeoID":3,"GeoType":"Borough","TimePeriodID":30,"ban_summary_flag":0,"Value":3.3,"CI":"","Note":"","DisplayValue":"3.3"},{"MeasureID":815,"GeoID":3,"GeoType":"Borough","TimePeriodID":31,"ban_summary_flag":0,"Value":3.6,"CI":"","Note":"","DisplayValue":"3.6"},{"MeasureID":815,"GeoID":3,"GeoType":"Borough","TimePeriodID":32,"ban_summary_flag":0,"Value":4.1,"CI":"","Note":"","DisplayValue":"4.1"},{"MeasureID":815,"GeoID":3,"GeoType":"Borough","TimePeriodID":177,"ban_summary_flag":0,"Value":2,"CI":"","Note":"","DisplayValue":"2.0"},{"MeasureID":815,"GeoID":3,"GeoType":"Borough","TimePeriodID":220,"ban_summary_flag":0,"Value":4.6,"CI":"","Note":"","DisplayValue":"4.6"},{"MeasureID":815,"GeoID":3,"GeoType":"Borough","TimePeriodID":221,"ban_summary_flag":0,"Value":3.5,"CI":"","Note":"","DisplayValue":"3.5"},{"MeasureID":815,"GeoID":3,"GeoType":"Borough","TimePeriodID":222,"ban_summary_flag":0,"Value":1.4,"CI":"","Note":"","DisplayValue":"1.4"},{"MeasureID":815,"GeoID":4,"GeoType":"Borough","TimePeriodID":15,"ban_summary_flag":0,"Value":4.3,"CI":"","Note":"","DisplayValue":"4.3"},{"MeasureID":815,"GeoID":4,"GeoType":"Borough","TimePeriodID":26,"ban_summary_flag":0,"Value":4.5,"CI":"","Note":"","DisplayValue":"4.5"},{"MeasureID":815,"GeoID":4,"GeoType":"Borough","TimePeriodID":28,"ban_summary_flag":0,"Value":3.9,"CI":"","Note":"","DisplayValue":"3.9"},{"MeasureID":815,"GeoID":4,"GeoType":"Borough","TimePeriodID":29,"ban_summary_flag":0,"Value":3.2,"CI":"","Note":"","DisplayValue":"3.2"},{"MeasureID":815,"GeoID":4,"GeoType":"Borough","TimePeriodID":30,"ban_summary_flag":0,"Value":3.3,"CI":"","Note":"","DisplayValue":"3.3"},{"MeasureID":815,"GeoID":4,"GeoType":"Borough","TimePeriodID":31,"ban_summary_flag":0,"Value":3.5,"CI":"","Note":"","DisplayValue":"3.5"},{"MeasureID":815,"GeoID":4,"GeoType":"Borough","TimePeriodID":32,"ban_summary_flag":0,"Value":3.7,"CI":"","Note":"","DisplayValue":"3.7"},{"MeasureID":815,"GeoID":4,"GeoType":"Borough","TimePeriodID":177,"ban_summary_flag":0,"Value":4.3,"CI":"","Note":"","DisplayValue":"4.3"},{"MeasureID":815,"GeoID":4,"GeoType":"Borough","TimePeriodID":220,"ban_summary_flag":0,"Value":4,"CI":"","Note":"","DisplayValue":"4.0"},{"MeasureID":815,"GeoID":4,"GeoType":"Borough","TimePeriodID":221,"ban_summary_flag":0,"Value":4.4,"CI":"","Note":"","DisplayValue":"4.4"},{"MeasureID":815,"GeoID":4,"GeoType":"Borough","TimePeriodID":222,"ban_summary_flag":0,"Value":4.1,"CI":"","Note":"","DisplayValue":"4.1"},{"MeasureID":815,"GeoID":5,"GeoType":"Borough","TimePeriodID":15,"ban_summary_flag":0,"Value":2.9,"CI":"","Note":"","DisplayValue":"2.9"},{"MeasureID":815,"GeoID":5,"GeoType":"Borough","TimePeriodID":26,"ban_summary_flag":0,"Value":2.3,"CI":"","Note":"","DisplayValue":"2.3"},{"MeasureID":815,"GeoID":5,"GeoType":"Borough","TimePeriodID":28,"ban_summary_flag":0,"Value":3.4,"CI":"","Note":"","DisplayValue":"3.4"},{"MeasureID":815,"GeoID":5,"GeoType":"Borough","TimePeriodID":29,"ban_summary_flag":0,"Value":4.6,"CI":"","Note":"","DisplayValue":"4.6"},{"MeasureID":815,"GeoID":5,"GeoType":"Borough","TimePeriodID":30,"ban_summary_flag":0,"Value":2.9,"CI":"","Note":"","DisplayValue":"2.9"},{"MeasureID":815,"GeoID":5,"GeoType":"Borough","TimePeriodID":31,"ban_summary_flag":0,"Value":2.9,"CI":"","Note":"","DisplayValue":"2.9"},{"MeasureID":815,"GeoID":5,"GeoType":"Borough","TimePeriodID":32,"ban_summary_flag":0,"Value":1.1,"CI":"","Note":"","DisplayValue":"1.1"},{"MeasureID":815,"GeoID":5,"GeoType":"Borough","TimePeriodID":177,"ban_summary_flag":0,"Value":3.6,"CI":"","Note":"","DisplayValue":"3.6"},{"MeasureID":815,"GeoID":5,"GeoType":"Borough","TimePeriodID":220,"ban_summary_flag":0,"Value":2.9,"CI":"","Note":"","DisplayValue":"2.9"},{"MeasureID":815,"GeoID":5,"GeoType":"Borough","TimePeriodID":221,"ban_summary_flag":0,"Value":2.9,"CI":"","Note":"","DisplayValue":"2.9"},{"MeasureID":815,"GeoID":5,"GeoType":"Borough","TimePeriodID":222,"ban_summary_flag":0,"Value":3,"CI":"","Note":"","DisplayValue":"3.0"},{"MeasureID":815,"GeoID":1,"GeoType":"Citywide","TimePeriodID":15,"ban_summary_flag":0,"Value":3.9,"CI":"","Note":"","DisplayValue":"3.9"},{"MeasureID":815,"GeoID":1,"GeoType":"Citywide","TimePeriodID":26,"ban_summary_flag":0,"Value":3.9,"CI":"","Note":"","DisplayValue":"3.9"},{"MeasureID":815,"GeoID":1,"GeoType":"Citywide","TimePeriodID":28,"ban_summary_flag":0,"Value":4,"CI":"","Note":"","DisplayValue":"4.0"},{"MeasureID":815,"GeoID":1,"GeoType":"Citywide","TimePeriodID":29,"ban_summary_flag":0,"Value":3.8,"CI":"","Note":"","DisplayValue":"3.8"},{"MeasureID":815,"GeoID":1,"GeoType":"Citywide","TimePeriodID":30,"ban_summary_flag":0,"Value":4,"CI":"","Note":"","DisplayValue":"4.0"},{"MeasureID":815,"GeoID":1,"GeoType":"Citywide","TimePeriodID":31,"ban_summary_flag":0,"Value":4.1,"CI":"","Note":"","DisplayValue":"4.1"},{"MeasureID":815,"GeoID":1,"GeoType":"Citywide","TimePeriodID":32,"ban_summary_flag":0,"Value":4.2,"CI":"","Note":"","DisplayValue":"4.2"},{"MeasureID":815,"GeoID":1,"GeoType":"Citywide","TimePeriodID":177,"ban_summary_flag":0,"Value":3.8,"CI":"","Note":"","DisplayValue":"3.8"},{"MeasureID":815,"GeoID":1,"GeoType":"Citywide","TimePeriodID":220,"ban_summary_flag":0,"Value":4,"CI":"","Note":"","DisplayValue":"4.0"},{"MeasureID":815,"GeoID":1,"GeoType":"Citywide","TimePeriodID":221,"ban_summary_flag":0,"Value":4.2,"CI":"","Note":"","DisplayValue":"4.2"},{"MeasureID":815,"GeoID":1,"GeoType":"Citywide","TimePeriodID":222,"ban_summary_flag":0,"Value":3.7,"CI":"","Note":"","DisplayValue":"3.7"}]
